Workbook

Sheet Temenos

Sheet Home
B2: Process Area | D2: Summary | E2: No of Processes
C3: Customer Relationship Management Processes | D3: CRM processes consist of customer on-boarding and associated processes such as KYC, AML and Campaign & Contact Management. It also includes Call Centre processes. | E3: =' (0) Customer Relationship Mgmt'!G3 -> 59 | G3: Note : Processes with Asterisk (*), are being used in more than one Vertical as Shortcut.
C4: Retail Banking Processes | D4: Retail Banking processes cover a range of service offerings such as Savings & Current Accounts, Deposits, Consumer Loans, Mortgages, Teller Transactions - including Cash, Currency Exchange, Travellers Cheques etc. Complete end-to-end processing is supported, from account opening/ loan origination, establishing lending arrangement, setting up of sweeps/ standing orders, and account/contract maintenance and closure. | E4: ='(1) Retail Banking Processes'!G3 -> 166
C5: Corporate Banking Processes | D5: Corporate Banking processes support Corporate Current and Deposit Accounts, Corporate Loans, Project Loans, Syndicated Lending, Correspondent Banking, Trade Finance & Guarantees, Factoring & Forfaiting Processes and Supply Chain Finance. | E5: ='(2) Corporate Banking Processes'!G3 -> 238
C6: Transactional Processes | D6: Transactional processes consist of Payments and Cheque Processing/ Clearing. These are normally performed at Back office as they are of high volume and operationally intensive in nature. | E6: ='(3) Transactional Processes'!G3 -> 496
C7: Treasury Processes | D7: Treasury processes support a range of vanilla (FX, MM) as well as Derivative products (FRAs, SWAPS, CCY Swaps etc). Customer position analysis, formulation of trading strategy, trade initiation, execution and settlement etc. are covered. | E7: ='(4) Treasury Processes'!G3 -> 79
C8: Private Wealth Management Processes | D8: Private Wealth Management processes covers the full life cycle of discretionary wealth management - from Asset Allocation & Portfolio Modeling, through Client Profiling, Maintenance/Review of portfolios, performance measurement and portfolio rebalancing. This process area also covers a range of processes related to Trading of Securities, Derivatives, Forex and Structured Products, as well as Mutual Funds, Fiduciary placements and administration processes such as Corporate Actions. | E8: ='(5) Private Wealth Management'!G3 -> 319
C9: Online Channels Processes | D9: Online Channels processes covers user set up and maintenance associated with Personal, Corporate and Wealth Management customers. It also includes processes specific to Retail, Corporate and Wealth Management as well as Transactional online channels processes. | E9: ='(6) Online Channels'!G3 -> 116
C10: Security Management (SMS) Processes | D10: Security Management System (SMS) processes include setting up and maintenance of users and user related parameters in the system. | E10: ='(7) Security Management (SMS)'!G3 -> 5
C11: Financial Accounting Parameter Processes | D11: Processes for maintaining parameters relating to financial accounting, accounting rules, set up of general ledger and financial reporting. | E11: ='(8) Financial Accounting'!G3 -> 34
C12: Core Parameter Processes | D12: Processes for setting up basic Transact parameters such as Interest, Fees and Tax related parameters. | E12: ='(9) Core Parameters'!G3 -> 9
C13: Islamic Banking Processes | D13: Islamic Banking Processes cover the work flow of Islamic model such as Asset Request, Approval and Purchase of Islamic Assets. Further it covers the end-to-end processing of Asset / Commodity Sale under different products such as Fixed Profit, Variable Profit and Multi Structured. Also it covers the work flow of Vendor / Supplier Payment. | E13: ='(10) Islamic Banking'!G3 -> 134
C14: Regionalized Solution Processes | D14: Regionalized Solution Processes cater to features that are specific to a particular country/ region. United Kingdom specific processes cover Customer Relationship Management, Financial Services Compensation Scheme (FSCS), Continuity of Access (COA), CRS, BACS Clearing, Clear Bank Interface and ISA / JISA accounts/ deposits service offerings. The United States specific processes cover Customer Relationship Management, Retail and Corporate service offerings. India specific processes cover Corporate service offerings. Australia specific processes cover Retail and Open banking service offerings. Peru specific processes cover Retail and Corporate service offerings. Argentina specific processes cover Retail and Corporate service offerings. Columbia specific processes cover Retail service offerings. Mexico specific processes cover Retail and Corporate service offerings. Hong Kong specific processes cover Retail service offerings. New Zealand specific processes cover Retail service offerings. Global specific processes to cover Retail and Corporate service offerings | E14: ='(11) Regionalized Solution'!G3 -> 268
C15: Digital Engagement Processes | D15: Digital Engagement processes caters to designing, planning and executing results-driven communications (Campaigns) across a variety of Online Channels (Internet and Mobile Banking) and Offline Channels (Email, Secure Message, SMS). Managing real time communication with Customers through Digital Channels is achieved through Digital Engagement User Agents Interfaces (front end applications - Campaign Management User Agent Interface and Campaign Administration User Agent Interface) | E15: ='(12) Digital Engagement'!G3 -> 22
C16: Regulatory Reporting and Compliance Processes | D16: Regulatory Reporting Processes cover the creation of FATCA/ CRS report setup, creation, generation and checking of reports. It also caters to customer personal data definition, searching and protection. Processes involved in loan management and restructuring have also been included. | E16: ='(13) Reporting and Compliance'!G3 -> 66
C17: Financial Crime Mitigation Processes | D17: Financial Crime Mitigation Processes covers the creation of Mandator and User for application and data restrictions. It also caters to creation of Customer on-boarding/ Enhanced due diligence form and creation of Risk Matrix for classification of risk. Knowledge Management allows user to create, generate and manage reports, schedule them and represent the generate reports as dashboards. | E17: ='(14) Financial Crime Mitigation'!G3 -> 74
C18: Fund Accounting Processes | D18: Fund Accounting Processes cover creation of Accounting Chart along with account definitions, structures, and transaction links. This structure is used as a basis for reporting and to produce financial statements. | E18: ='(15) Fund Accounting Processes'!G3 -> 69
C19: Temenos Digital Processes | D19: Temenos Digital Processes covers customer on-boarding , retail and corporate services such as managing account , beneficiary, cheques, lending etc. | E19: ='(16) Digital Banking (Infinity)'!G3 -> 46
C20: Temenos Banking Solution (TBS) Processes | D20: Temenos Banking Solution (TBS) Processes Retail Lending Fulfillment Service (RFS) covers the creation, disbursement, and repayment of Loans. Retail Deposits Banking Service (RDBS) covers the opening & closing of Accounts, Term Deposits, Transferring funds, maintenance, closure of the Accounts/ Term Deposits, Alerts, Multi-Currency Accounts and Multi-Company Groups. Target Instant Payment System (TIPS) Service covers outward remittance, inward credit transfers, and the cancellation of payments. Temenos Enterprise Pricing (TEP) covers Creating package arrangements for pricing benefits, closing the package, updating negotiated price and capturing relationships for relationship pricing. Buy Now Pay Later (BNPL) covers financing options for their retail customers, from Customer registration, Loan creation to Loan cancellation and refund. It also supports the amendment and closure of Facilities and loans. | E20: ='(17) Temenos Banking Solution'!G3 -> 75
C21: Business Banking Processes | D21: Business Banking processes cover a range of service offerings such as Accounts, Deposits, Loans, Asset Finance products that serve the needs of the Small Medium Enterprise (SME) segment. | E21: ='(18) Business Banking Processes'!G3 -> 34
C22: Enterprise Services Processes | D22: Enterprise Services Processes Retail Enterprise Services (RES) covers the opening and closing of Accounts, Term Deposits, Transferring funds, maintenance, closure of the Accounts/ Term Deposits, Multi-Currency Accounts and lending with payment capabilities. Business and Corporate Enterprise Service (BCES) covers the opening and closing of Accounts, Term Deposits, Transferring funds, maintenance, Payments, closure of the Accounts/ Term Deposits, Cash Management, Trade Finance & Guarantees and lending. | E22: ='(19) Enterprise Services'!G3 -> 157
C23: Financial Risk Management Processes | D23: Financial Risk Management illustrates various approaches or methodologies for risk management using reporting tools and techniques. | E23: ='(20) Financial Risk (FRM) '!G3 -> 19
C24: Platform Based Approach Processes | D24: The platform-based approach processes provides a comprehensive and detailed understanding of user journeys within Transact - Core Banking, Payments, Loans, Wealth, Corporate, Trade Finance, Treasury, Financial Crime Mitigation, Cash Management packages. | E24: ='(21) Platform Based Approach'!G3 -> 275
E25: =SUM(E3:E24) -> 2760

Sheet  (0) Customer Relationship Mgmt
D2: Business Area | E2: Customer Relationship Management | G2: In Scope
D3: Total no of processes | E3: =COUNTIF(E8:E79,"*") -> 59 | G3: =COUNTIF(G8:G79,"Yes") -> 59
D4: Release | E4: R25 Model Bank
G6: Scoping
B7: Process Area | C7: Scenario | D7: Process | E7: Process Description | G7: In Scope
B8: Customer Relationship Management Processes
C9: 0.1 Retail Banking Clients | G9: =COUNTIF(G10:G11,"Yes") -> 2
D10: Create Retail Customer (PW) | E10: This process describes the activities for Customer creation, using a PW Process. Process is initiated from the home page. | G10: Yes
D11: Manage Customer Engagements (Retail) | E11: Front Office user checks on the customer's request and validate his existence in the system. New customers will be recorded as prospects before continuing with AML and KYC check. Existing customer's records will be checked for cross-selling opportunities and verified if background checks or record updates are required. The Customer on boarding feature enables the user to choose the activity to be performed based on the status of the prospect/ Customer (existing or new). | G11: Yes
C12: 0.2 Corporate Banking Clients | G12: =COUNTIF(G13:G20,"Yes") -> 8
D13: Amend Customer Charge (Corporate) | E13: This process is used to amend Customer charge. | G13: Yes
D14: Amend Customer Details (Corporate) | E14: This process carries out requests to amend customer related data viz., change customer details or add/ remove additional addresses as well change of the customer status. | G14: Yes
D15: Complete KYC Check (Corporate) | E15: KYC documents are obtained from the customer and checked against a KYC Checklist. For missing documents follow up actions are captured. | G15: Yes
D16: Create Customer Record (Corporate) | E16: Once the required background checks are completed, the user creates/ updates the customer record. All inputs in the system will be approved by a Supervisor. Subsequently, scanned documents are attached to the customer record. This process is repeated for all associated entities. | G16: Yes
D17: Manage Customer Engagements (Corporate) | E17: This process begins when the Relationship Manager obtains all required documents from the customer. New customers will be recorded as prospects, before continuing with AML and KYC checks. In case of existing customers, checks are made to see if any KYC/AML updates are required. The Customer onboarding feature enables the user to choose the activity to be performed based on the status of the prospect/ Customer (existing or new). | G17: Yes
D18: Perform AML Check (Corporate) | E18: This process deals with carrying out AML Blacklist checks on databases like OFAC (Office of Foreign Assets Control) or PEP (Politically Exposed Persons). The results from such checks are captured in the customer record. | G18: Yes
D19: Set or Remove Posting Restrict (Corporate) | E19: This process covers executing a Customer's request or an external/ internal request for setting/removing restrictions for posting. The restriction can be set either at the Customer level or at an account level. | G19: Yes
D20: Set Up Mandates and Signatory Groups | E20: The process depicts the set up of signatory groups and mandates. Customer is attached to respective signatory group. Mandate Application group is formed by logically grouping Transact applications/ versions. The mandate requirement can be defined for customer, account or portfolio and in turn linked to the appropriate application group and mandates. | G20: Yes
C21: 0.3 Private Wealth Management Clients | G21: =COUNTIF(G23:G34,"Yes") -> 10
D22: 0.3.1 Customer Creation
D23: Create Customer Record (PWM) | E23: This process describes the activities for Customer creation, using a PW Process. Once the required background checks are completed, the user creates/ updates the Customer record. Subsequently, scanned documents are attached to the customer record. This process is repeated for all associated entities. | G23: Yes
D24: Generate Documents For Suggested Investment Strategies | E24: Once an investment strategy is defined, the Relationship Manager will generate all required documents, including model portfolios and a confirmation is sought from the client. | G24: Yes
D25: Manage Customer Engagements (PWM) | E25: Relationship Managers will initiate a client on-boarding process where they capture prospect data. This data is subsequently validated by the supervisor. Once approved the RM will complete the prospect record and initiate the required background checks. If the prospect or customer already exists, a handover is performed. | G25: Yes
D26: Perform AML or KYC Check (PWM) | E26: KYC documents are obtained from the customer and checked against a KYC Checklist. For missing documents follow up actions are captured. | G26: Yes
D27: Perform Customer Risk Profiling | E27: Once all required background checks are completed the investment representative will perform MiFID risk profiling, wherever applicable, and investment risk profiling for the client in order to generate an investment proposal. | G27: Yes
D28: 0.3.2 Portfolio Opening
D29: Build Portfolio | E29: Once the Customer portfolio is created, a further request can be placed to create a new portfolio of securities. Customer confirms the amount for which this portfolio needs to be built. Based on the amount and investment strategy, bank provides a basket of possible securities for Customer's portfolio. Once the basket of suggested securities is approved by the Customer, this portfolio is used by the bank to initiate and execute trade orders. | G29: Yes
D30: Open Customer Portfolio | E30: After a Customer record is created in the system, the Customer portfolio is set up with required restrictions. The assets are subsequently transferred into Customer's account. If Customer requests for building portfolio, the portfolio is built based on the amount committed and strategy selected by the Customer. | G30: Yes
D31: Set Block and Restrictions | E31: Investment Representative decides on the type of restrictions to be set (Holding/ Transaction restriction) by inputting the appropriate portfolio restrictions. | G31: Yes
D32: Set PWM Alerts | E32: After the Customer portfolio is created and authenticated, Customer alert preferences are captured in the system. Based on this setup and occurrence if the event(s), Customer is sent appropriate alerts through the selected delivery channels. | G32: Yes
D33: 0.3.3 Portfolio Closing
D34: Close Customer Portfolio | E34: Request for closure triggers a series of actions viz., marking of closure in customer's portfolio, collection of fees/ charges and transfer of assets from the client's account. | G34: Yes
C35: 0.4 Islamic Banking Clients | G35: =COUNTIF(G36:G37,"Yes") -> 2
D36: Create Customer (Islamic) | E36: This process describes the activities involved in Customer creation, once the required background checks are completed, the user creates/ updates the customer record. AML and KYC checks are done and documents received from customer are scanned and attached to the customer record. | G36: Yes
D37: Manage Customer Engagements (Islamic) | E37: This process begins with Front Office user checking on the customer's request and validating if the customer is already registered in the system. New customers will be recorded as prospects before continuing with AML and KYC check. Existing customer's records will be checked for cross-selling opportunities and verified if background checks or record updates are required. | G37: Yes
C38: 0.5 Financial Institutions | G38: =COUNTIF(G39:G45,"Yes") -> 7
D39: Amend Routing Instructions | E39: New settlement instructions need to be verified, approved and updated in the system. | G39: Yes
D40: Create Bank Customer | E40: This process deals with the creation of a Bank Customer record in the system. | G40: Yes
D41: Create Routing Instructions | E41: Once a record for a Financial Institution is created and settlement instructions obtained, routing instructions are captured in the system. | G41: Yes
D42: Generate or View Statement MT942 | E42: Based on the parameter setting, MT942 can be generated for the transactions processed in the account. This may contain transactions happened during the day or from the last statement generated time, or can be filtered based on the amount of transaction, as per setup. | G42: Yes
D43: Open Internal Account * | E43: This process depicts the activities associated with setting up of internal accounts of the Bank, which are in the nature of own-book accounts. | G43: Yes
D44: Open Nostro Account | E44: This process describes activities associated with setting up a Nostro account. | G44: Yes
D45: Open Vostro Account | E45: This process describes activities associated with setting up a Vostro account. | G45: Yes
C46: 0.6 Contact Management | G46: =COUNTIF(G47:G54,"Yes") -> 8
D47: Amend Contacts (Retail) | E47: This process describes, how contacts that have been logged, can be amended in Transact. | G47: Yes
D48: Capture Customer Travel Details | E48: This process describes the steps involved in capturing Customer Travel plans. Travel details like place of travel, time of travel, purpose of travel are captured to help in internal decision making. Customer Travel details are taken into consideration while arriving at marketing strategies, offering suitable product and services to the customers. | G48: Yes
D49: Manage Contacts (PWM) | E49: This process describes how Front Office staff manages customer contacts with Transact Contact Management functionalities. Users can record call reports, schedule appointments, record tasks and/or register complaints. | G49: Yes
D50: Manage Contacts (Retail) | E50: This process describes how Front Office staff manages customer contacts with Transact Contact Management functionalities. Users can record call reports, schedule appointments, record tasks and/or register complaints. | G50: Yes
D51: Manage Customer Complaints (PW) | E51: The process depicts the tasks involved in managing complaints from the customer through a dedicated process workflow. | G51: Yes
D52: Manage Customer Contacts (Call Centre) | E52: The process describes Call Centre Agent's activities for managing customer contacts/ requests. It also includes Cross Selling Opportunities. | G52: Yes
D53: Manage Customer Service Requests (PW) | E53: The process depicts the tasks involved in managing service requests coming in from the Customer through the Call centre. | G53: Yes
D54: Manage Customer Travel Details | E54: This process describes the steps involved in amending Customer Travel details. Travel notifications are marked as expired and moved to history automatically on reaching the travel end date. Unexpired Travel notifications can be manually cancelled and moved to history. | G54: Yes
C55: 0.7 Campaign Management | G55: =COUNTIF(G56:G57,"Yes") -> 2
D56: Manage Campaigns | E56: Campaign proposals are drafted/ approved and captured. Campaigns can be outbound using defined delivery channels or inbound in which case only opportunities are generated. Opportunities that are accepted will trigger pre-defined workflows that the user will execute. | G56: Yes
D57: Manage Opportunity Definitions | E57: In order to manage campaigns in Transact, users needs to perform a series of administrative functions to set up the basic parameters that will be used when new campaign is launched. These also include the definition of opportunities, setting up of rules and definition of workflows. | G57: Yes
C58: 0.8 CRM Administration | G58: =COUNTIF(G59:G62,"Yes") -> 4
D59: Change Customer Group | E59: Multiple relationships between customer and/ or person entities are defined in PARTY.RELATIONSHIP. For each party relationship, it will be possible to define the direction (Parent/Child/Other entity) of the relationship. This party relationship can be imported into CUSTOMER.GROUP based on the Party ID. This process describes the steps involved in amending customer relationships defined in PARTY.RELATIONSHIP and the automatic creation of CUSTOMER.GROUP.CHANGE with the proposed addition or deletion of customer from the associated CUSTOMER.GROUP. The proposed addition or deletion of customers in the group can be accepted or rejected in CUSTOMER.GROUP.CHANGE. Transact service will update CUSTOMER.GROUP with proposed changes that were accepted in CUSTOMER.GROUP.CHANGE | G59: Yes
D60: Maintain Customer Relationships | E60: Transact allows the user to capture details of prospects and maintain the relationships between customers using this process. Prospects can be individuals or corporate entities. | G60: Yes
D61: Set Up Customer Group | E61: This process describes the steps involved in creating customer groups for different purposes. The below parameters needs to be set before creating a customer group: - Define Natural relation and Group relation in RELATION table. - Set-up multiple relationships between customer and/or person entities in PARTY.RELATIONSHIP. For each party relationship it will be possible to define the direction (Parent/Child/Other entity) of the relationship. This party relationship can be imported into CUSTOMER.GROUP based on the Party ID. - Customer grouping can be used for different purposes (e.g. Operational, household) this is configured in CUST.GROUP.PURPOSE. The Group Purpose will contain rules about where the customer group can be used, and how customers and parties in the group can be stored. Operational(Risk) purpose can be used for limit allocation. Sub-Groups can also be created and are used when presenting views of the risk group providing the ability to aggregate members of the sub-group. | G61: Yes
D62: Set Up Customer Profiles | E62: Customer profile types are defined and set up in Transact with specific profiling rules being recorded for each profile type. During the creation of a customer record these profiles are linked to a customer. | G62: Yes
C63: 0.9 Common Processes | G63: =COUNTIF(G64:G78,"Yes") -> 15
D64: Amend Customer Charge | E64: The process deals with updating of the Charge group to which Customer belongs. Transact by default based on the setup, allocates a charge group to the customer on creation of customer record. However, it can be updated at a later stage, which is handled through this process. Based on the charge group to which customer is associated, charges will be taken during transaction. | G64: Yes
D65: Amend Customer Details | E65: This process carries out customer requests to amend customer related data viz., change customer details or add/ remove additional addresses, registering Deceased customer details like date when the customer died, the date when the bank is notified about the death and date of granting Probate. It also covers the "termination" of a customer relationship (change of status to 51). | G65: Yes
D66: Amend or Reverse Mass Block | E66: This process is to Amend/ Reverse the existing blocked Customer/ Group of Customers/ Accounts/ Bundle Arrangements along with its corresponding Currency Top Accounts. | G66: Yes
D67: Initiate Bundle Arrangement Block | E67: This process is to Block a Bundle Arrangement. Blocking a Bundle Arrangement will block its corresponding Currency Top Accounts. Once blocking is in place, this would be checked during transaction processing, which would then raise an override/ error (can be configured). | G67: Yes
D68: Initiate Bundle Arrangement Unblock | E68: This process explains Unblocking of blocked Bundle Arrangement along with its corresponding Currency Top Accounts. | G68: Yes
D69: Initiate Customer Mass Block | E69: This process is to mark Blocking for a Customer/ Group of Customers/ Accounts based on Customer/ Account criteria. Once the blocking is in place, this would be checked during transaction processing, which would then raise an override/ error (can be configured). | G69: Yes
D70: Initiate Customer Mass Unblock | E70: This process is to Unblock for a Customer/ Group of Customers/ Accounts from the existing blocked ID's. | G70: Yes
D71: Manage Customer Dormancy | E71: Customer Dormancy status is updated as "Dormant” or “Watchlist” based on the status of the underlying products owned by the customer. The customer is considered dormant when there is no customer induced activity with the bank or with any external systems for a pre-defined dormancy period. Products considered for dormancy determination are monitored during the period of inactivity and at the end of the period, the customer is considered dormant in case of no activity. | G71: Yes
D72: Manage Document and Image Upload | E72: The process describes the activities for uploading images and documents for customers into Transact. | G72: Yes
D73: Manage Documents | E73: The process describes the activities for recording new customer documents or amending existing customer documents. | G73: Yes
D74: Re-open Closed Customer | E74: This process describes the activities to be performed to re-open the customer record that has been marked as closed. | G74: Yes
D75: Close Customer | E75: This process describes the activities involved in the closure of a customer record. Pre-closure checks are run to identify whether the customer has any active financial and non-financial contracts (relationships links in accounts). Exit status and exit reason are captured before closing the customer record. | G75: Yes
... D79: Perform Currency Exchange Rate Backdating | E79: This process describes the activities involved in the creation of a backdated currency exchange rate. This also covers the storing and maintenance of history of dates when backdated currency exchange rates were defined or modify. | G79: Yes

Sheet (1) Retail Banking Processes
D2: Business Area | E2: Retail Banking | G2: In Scope
D3: Total no. of processes | E3: =COUNTIF(E8:E215,"*") -> 166 | G3: =COUNTIF(G8:G215,"Yes") -> 166
D4: Release | E4: =' (0) Customer Relationship Mgmt'!E4 -> R25 Model Bank
G6: Scoping
B7: Process Area | C7: Scenario | D7: Process | G7: In Scope
B8: Retail Banking Processes
C9: 1.1 Account and Deposit Processes | G9: =COUNTIF(G10:G61,"Yes") -> 48
D10: 1.1.1 Accounts and Deposits
D11: Create Arrangement Account | E11: This Process depicts receipt of an arrangement (AR) account opening form from the customer along with an initial deposit. Successful opening of the AR account leads to associated sub processes viz., issue of debit card, cheque book issue, set up standing instruction/ sweep, set up overdraft limit etc. | G11: Yes
D12: Create Limit Arrangement Account | E12: This Process depicts creation of a Limit Arrangement account for the purpose of calculating charges on Limit balances. Limit Arrangement created, needs be attached as Charge Account in the Limit set for the customer's Current Account Arrangement. | G12: Yes
D13: Create Product Bundle | E13: The process details out the tasks involved in the bundling various products like Off set mortgage, interest compensation, interest upgrade, bonus interest, pooling of accounts etc. | G13: Yes
D14: Issue Cheque Book | E14: This process describes issue of cheque book to the customer either as a part of account opening process or on receipt of an ad hoc request. | G14: Yes
D15: Issue Debit Card | E15: This process describes Debit card issue as part of account opening or on receipt of an adhoc request. | G15: Yes
D16: Issue Passbook | E16: The process relates to issuance of a passbook to a new Customer or to an existing Customer on a specific request. | G16: Yes
D17: Open Deposit (AA) | E17: This process describes activities involved in the creation and funding of a fixed deposit/ bond (Fixed/ Floating/ Short term/ Long term etc.). Deposit funding can be through fund transfer, cash or using payment order based on captured beneficiary details | G17: Yes
D18: Open Discounted Deposit (AA) | E18: This process describes creation and funding of a discounted (interest paid in advance) fixed deposit/ bond (Fixed/ Floating/ Short term/ Long term etc.) through "AA" module. | G18: Yes
D19: Open Safe Deposit Box (SDB) | E19: This process describes creation and funding of a Safe Deposit Box through the "AA" module. | G19: Yes
D20: 1.1.2 Account or Deposit Administration
D21: Amend Arrangement Account | E21: This process describes the receipt of an amendment request for an arrangement account from the Customer and capturing the amendments in the system. The amendment can also be bank initiated. Amendments related to change product/ account details/ holding pattern or to set dormancy/ posting restrict or to renegotiate arrangement/ adjust balances and bills of an arrangement account is done through new activity option in AA overview. | G21: Yes
D22: Amend Deposit (AA) | E22: This process describes the activities involved in the amendment of a deposit based on a Customer request. | G22: Yes
D23: Amend Product Bundle | E23: The process details out the tasks involved in amending the product bundle created for a Customer. | G23: Yes
D24: Block or Unblock Funds | E24: This Process describes blocking and unblocking of funds for an account, for a specific period and amount. | G24: Yes
D25: Cancel Account Sweep | E25: This process describes the cancellation of sweep set up for an account. | G25: Yes
D26: Change Interest and Payment Schedule (AA) | E26: This process describes how to change Debit/ Credit Interest and Interest Payment Frequency (Payment Schedule) for an Arrangement Account. | G26: Yes
D27: Change Primary Customer (AA) | E27: This process describes how to change a Primary Customer for an Arrangement Account. | G27: Yes
D28: Close Arrangement Account (AA) | E28: The process describes the activities involved in the closure of an arrangement account. Customer request is received along with the unused deliverables (chequebook, debit card, etc.). The details are captured in the system and the closure activities are completed. Account closure can be settled either through cash, account transfer, or payment order. | G28: Yes
D29: Close Safe Deposit Box (SDB) | E29: The process begins with the receipt of an Safe Deposit Box arrangement closure request along with the deliverables (Keys etc.). The details are captured in the system and the closure activities are completed. The user has an option to pay the Safe Deposit Box arrangement closure proceeds in three modes, namely account transfer, teller and funds transfer. | G29: Yes
D30: Generate Account Statements | E30: This process describes handling of a customer request for an account statement (Current period/ Past period /Ad-hoc). | G30: Yes
D31: Generate Deposit Advices | E31: This process describes generation of an ad hoc deposit advice (AA). | G31: Yes
D32: Generate MT112 - Status of Request for Stop Payment of a Cheque | E32: This Process is to generate MT112 - which is sent by the drawee bank (on which a cheque is drawn) to the drawer bank or the bank acting on behalf of the drawer bank with the details of action that have been taken while stop payment of a cheque as referred in the Message. | G32: Yes
... D54: Process Incoming Statement Request | E54: This process describes the activities involved in receiving statement requests as incoming MT920. Corresponding statement response is generated either through STP (Straight Through Process) or COB (Closure of Business) as per the frequency set up in ACCOUNT.STATEMENT application. Based on the statement request, an outward statement response (MT940, 941, 942 & 950) is generated. | G54: Yes
D55: 1.1.3 Product Administration
D56: Create Product * | E56: This process describes the activities for setting up a product under the hierarchy of a product group. The product conditions are created or existing conditions are re-used and linked to a property. Subsequently the product set up is validated (proofed) and published, i.e., the product is now available for users to start creating arrangement(s). The same process can be used for amending the product also. | G56: Yes
D57: Create Product Group * | E57: This process describes the activities for setting up a product group under a product line. The Product Build set up under Arrangement Architecture is hierarchical and allows the derivation of product structures from higher levels. For example, a Product (e.g. 15 year Fixed Rate Mortgage) will be derived from a Product Group (e.g. Mortgages), which will be derived from a Product Line (e.g. Lending). In addition to this structural hierarchy, the Product Builder enables the definition of “families” of products through Product Inheritance. The purpose of a Product Group is to provide a structure and constraints to any product derived from the group. The same process can be used for amending the product group. | G57: Yes
D58: 1.1.4 Retail PW Processes
D59: Add Joint Holder To Account (PW) | E59: This process indicates the activities of a Branch User, to add a joint holder to an existing account. | G59: Yes
D60: Issue Cheque Book And Debit Card (PW) | E60: The process describes the activity of capturing cheque book issue details and debit card issue details. | G60: Yes
D61: Open Account (PW) | E61: The process describes various steps involved in account opening and account related services like capturing debit card details. | G61: Yes
C62: 1.2 Teller Processes | G62: =COUNTIF(G64:G118,"Yes") -> 40
D63: 1.2.0 Teller Financial Services
D64: Receive or Execute Teller Financial Services | E64: This process facilitates capture of information for all teller financial services (TFS) in one screen, creates a consolidated entry (if parameterised) on the Customer account, a consolidated charge and a consolidated transaction advice. It is also possible to capture all information in one screen of TFS and create separate entries in the Customer's account for each of them. | G64: Yes
D65: Reverse Teller Financial Services Transactions | E65: This process facilitates reversal of all teller financial services (TFS), captured previously, in one screen. Also, a consolidated entry (if parameterised) on the Customer account, a consolidated charge and a consolidated transaction advice can be generated. It is also possible to create separate entries in the Customer's account for each of reversal. | G65: Yes
D66: 1.2.1 Cash transactions
D67: 1.2.1.1 Cash Deposits
D68: Execute FCY Cash Deposit | E68: This process is used to deposit Foreign Currency Cash into an account resulting in the generation of a transaction receipt. | G68: Yes
D69: Execute LCY Cash Deposit | E69: This process is used to deposit Local Currency Cash into an account resulting in the generation of a transaction receipt. | G69: Yes
D70: 1.2.1.2 Cash Withdrawals
D71: Execute FCY Cash Withdrawal | E71: This process describes Foreign Currency Cash withdrawal from an account. | G71: Yes
D72: Execute LCY Cash Withdrawal | E72: This process describes Local Currency Cash withdrawal from an account. | G72: Yes
D73: 1.2.1.3 Currency Exchange
D74: Execute Buy FCY Against LCY Cash | E74: This process describes purchase of Foreign Currency Cash from a customer and handing over the equivalent local currency. | G74: Yes
D75: Execute FCY Exchange | E75: This process describes the exchange of FCY, using Teller application. | G75: Yes
D76: Execute Sell FCY Against LCY Cash | E76: This process describes sale of Foreign Currency Cash to a customer after receiving the equivalent local currency. | G76: Yes
D77: Capture Purchase of FCY from Customer | E77: The process begins with the receipt of request from a Customer, for purchase of Foreign Currency Cash by the bank (Customer sells FCY/ Bank purchases FCY). The request is validated and the exchange rate is confirmed to the Customer. | G77: Yes
D78: Receive Request For FCY Exchange | E78: The process begins with the receipt of request from a Customer for foreign currency exchange. The request is validated and the exchange rate is confirmed to the Customer. | G78: Yes
D79: Capture Sale of FCY to Customer | E79: The process begins with the receipt of request from a Customer, for sale of Foreign Currency Cash by the bank (Bank sells FCY/ Customer purchases FCY). The request is validated and the exchange rate is confirmed to the Customer. | G79: Yes
D80: 1.2.1.4 Denominations
D81: Change Denominations | E81: This process involves a Teller accepting cash and exchanging it for different denominations. | G81: Yes
D82: 1.2.2 Travellers Cheques
D83: 1.2.2.1 Travellers Cheque Purchase
D84: Execute Travellers Cheque Encashment | E84: This process describes activities associated with purchase of Travellers cheques from a Customer in exchange for local currency. | G84: Yes
D85: Receive Travellers Cheque Encashment Request | E85: This process involves carrying out physical authentication of Travellers Cheque received from a Customer. | G85: Yes
D86: 1.2.2.2 Travellers Cheque Sale
D87: Execute Travellers Cheque Sale | E87: This process describes activities associated with sale of Travellers cheques to a Customer in exchange for local currency. | G87: Yes
D88: Receive Travellers Cheque Sale Request | E88: This process involves activities associated with authentication of request in case of sale of Travellers cheques to a Customer. | G88: Yes
D89: 1.2.3 Teller Administration
D90: 1.2.3.1 Till Administration
D91: Change Till User | E91: This process is used to change Till to a different user/ teller. | G91: Yes
D92: Create New Till | E92: This process is used to create a new Till and assigning the till to a teller. | G92: Yes
D93: Reopen Till | E93: This process describes activities for reopening a Till as part of Start of Day activity of the Head Teller. | G93: Yes
D94: 1.2.3.2 Till Transfer
D95: Evaluate Cash Position In Vault | E95: This process involves evaluating the available cash position in vault and deciding on the further course of action, viz., (1) Cash required from Central Bank (2) Cash to be remitted to Central Bank or (3) Cash sufficient for operations. | G95: Yes
D96: Receive Cash From Central Bank | E96: This process involves for raising a request to Central Bank for cash requirement, receiving and accounting for the cash remittance. | G96: Yes
D97: Remit Cash To Central Bank | E97: This process describes placing a request for cash remittance to Central Bank, dispatching and accounting for the cash remittance. | G97: Yes
D98: Transfer Cash Between Tills | E98: This process describes the activities relating to the transfer of cash from one teller to another teller. | G98: Yes
D99: Transfer Cash From Till To Vault | E99: The process involves transfer of cash from Till (teller) to the vault. | G99: Yes
D100: Transfer Cash From Vault To Till | E100: This Process describes the transfer of cash from Vault (by Head teller) to Till (Teller). | G100: Yes
D101: 1.2.3.3 Travellers Cheque Admin
D102: Manage Receipt of Travellers Cheque Stock | E102: Process for recording stock of Travellers Cheques on receipt from Head Office. | G102: Yes
D103: Transfer Travellers Cheque Stock to Other Branches | E103: Process involves receipt of an authenticated request and transfer of Travellers Cheques stock to another branch. | G103: Yes
D104: Transfer Travellers Cheque Stock from Vault To Till | E104: Process describes transferring stock of Travellers Cheques from vault to Till (Teller). | G104: Yes
D105: 1.2.4 End of Day Activities
D106: Perform End of Day Activities - Close Till | E106: This process describes the day end activities performed by a Teller in relation to cash and Travellers Cheque Balancing and closure. | G106: Yes
D107: Perform End of Day Activities - Nostro Funding For Travellers Cheques Issued | E107: This process involves activities that a Teller has to perform for funding the Nostro account towards Travellers Cheques issued during the day and advise correspondent Bank accordingly. | G107: Yes
D108: 1.2.5 Common Processes
D109: Issue Passbook * | E109: The process relates to issuance of a passbook to a new Customer or to an existing Customer on a specific request. | G109: Yes
D110: Update Passbook * | E110: This process describes the activities in printing and updation of a customer passbook. | G110: Yes
D111: Verify Cash Deposit Transaction Limits | E111: The process shows automatic steps executed by the system during a cash deposit transaction. The Role based transaction limits, User group's authorisation/ override management and Authorisation levels are configured as part of the implementation requirement of the client Bank. The Model Bank system is configured for - 1 level of Authorisation for majority of transactions (with exceptions such as 'Link collateral to limit' etc.) - The users rights are configured to accept overrides and input transactions without restrictions. | G111: Yes
D112: Verify Transaction Limits | E112: The process shows automatic steps executed by the system while executing the following processes: 1. Execute LCY Cash withdrawal 2. Execute FCY Cash withdrawal 3. Execute Travellers cheque encashment 4. Execute Travellers cheque sale 5. Execute Sell FCY against LCY cash 6. Execute Buy FCY against LCY cash. The Role based transaction limits, User group's authorization/ override management and Authorization levels are configured as part of the implementation requirement of the client Bank. The Model Bank system is configured for - 1 level of Authorization for majority of transactions (with exceptions such as 'Link collateral to limit' etc.) - The users rights are configured to accept overrides and input transactions without restrictions. | G112: Yes
D113: 1.2.6 Drafts
D114: Process Cancellation of LCY Draft | E114: This process deals with Cancellation of an issued Drafts based on Customer request. | G114: Yes
D115: Issue of LCY Draft (Retail) | E115: The process explain the steps involved in issuance of LCY draft at the teller counter. All necessary authentications are done before the draft is issued. The system updates the draft stock inventory upon issuance. | G115: Yes
D116: Receive Request To Issue Draft * | E116: The process is initiated on receipt of the draft/ bankers' cheque request by the front office. The request is then forwarded to the back office for further processing. | G116: Yes
D117: Revoke Stop Payment of LCY Draft (Teller) | E117: This process deals with Revoke a stopped draft based on Customer request. | G117: Yes
D118: Stop Payment of LCY Draft | E118: This process deals with stop payment of an issued Drafts based on Customer request. | G118: Yes
C119: 1.3 Lending Processes | G119: =COUNTIF(G121:G174,"Yes") -> 46
D120: 1.3.1 Personal Loan
D121: Check Eligibility (Personal Loan) | E121: This process begins with receipt of personal loan application from the front office and performing basic Customer and product eligibility checks. | G121: Yes
D122: Perform External Credit Scoring (PL) | E122: The process describes the various steps to perform an external credit check and calculate credit score, for a personal loan. | G122: Yes
D123: Perform Internal Credit Scoring (PL) | E123: The process describes the various activities to perform an internal credit check and calculate credit score, for a personal loan. | G123: Yes
...

Sheet (2) Corporate Banking Processes
D2: Business Area | E2: Corporate Banking | G2: In Scope
D3: Total no. of processes | E3: =COUNTIF(E8:E299,"*") -> 238 | G3: =COUNTIF(G8:G299,"Yes") -> 238
D4: Release | E4: ='(1) Retail Banking Processes'!E4 -> R25 Model Bank
G6: Scoping
B7: Process Area | C7: Scenario | D7: Process | E7: Process Description | G7: In Scope
B8: Corporate Banking Processes
C9: 2.1 Accounts and Deposits | G9: =COUNTIF(G11:G74,"Yes") -> 56
D10: 2.1.1 Current Account
D11: Complete Corporate Current Account Opening | E11: This process relates to handing over current account deliverables (cheque book, debit card etc.) to the customer. The signatories and mandate of the Customer(s) is/ are captured as part of this process. | G11: Yes
D12: Create Current Account Arrangement (Corporate) | E12: The process describes the steps associated with creation of corporate current account arrangement (AR). After successful authorization, the account opening is done which leads to other processes viz., verify external cheque, account to account transfer etc. | G12: Yes
D13: Issue Cheque Book (Corporate) | E13: This process describes the issue of cheque book to the Corporate customer, either as a part of the account opening process or on receipt of an ad hoc request. | G13: Yes
D14: Issue Debit Card (Corporate) | E14: This process describes the issue of Debit Card either as a part of the account opening process or on receipt of an ad hoc request. | G14: Yes
D15: Manage Account Conditions (Corporate) | E15: The process describes the activities related to the maintenance of account specific conditions. | G15: Yes
D16: Manage Account To Account Transfer (Corporate) | E16: The process describes the requests received from Customers at the front office for account to account transfers within the bank. The transactions are performed by the teller after making the necessary checks and authentications. | G16: Yes
D17: Manage Mandates (Corporate) | E17: This process describes the activities involved in capturing signatory group, mandates, mandate application group and attaching them to mandate requirements. Validations are performed against the mandate when a transaction is executed for respective customer, account or portfolio. | G17: Yes
D18: Open Current Account - PW (Corporate) | E18: This process describes the opening of a current account (incl. mandates and issuing of a cheque book), using a PW process. | G18: Yes
D19: Open Current Account (Corporate) | E19: The process describes the steps associated with the opening of a Corporate Current account. Successful authorisation of account opening leads to other processes viz., image capture, initial deposit, issue of cheque book, set up Overdraft limit etc. | G19: Yes
D20: 2.1.2 Deposits
D21: Open Contract Based Deposit - PW (Corporate) | E21: This process describes creation of a "Contract" based fixed deposit (Fixed/ Floating/ Discounted etc.) through the "LD module" using PW. | G21: Yes
D22: Open Contract Based Deposit (Corporate) | E22: This process describes creation of a "Contract" based fixed deposit (Fixed/ Floating/ Discounted etc.) through the "LD module". | G22: Yes
D23: 2.1.3 Cash Management
D24: Cancel Account Sweep (Corporate) | E24: This process describes the cancellation of sweep set up for an account. | G24: Yes
D25: Create External Arrangement Account | E25: This Process describes the creation of an External Arrangement account for the purpose of external Sweeps. Arrangement accounts are set up with linked account number, which will be nostro accounts (beneficiary). The purpose of the external Arrangement account is to act as a Link Account in the Cash pool record in-order to facilitate sweep of funds from the source account to an external account via payment order. | G25: Yes
D26: Create Investment Arrangement Account | E26: This Process describes the creation of an Investment account for the purpose of Investment Sweeps. The Investment products are created with the principal balance as memo balance and other balances as real balance. The purpose of Investment account is to enable the customers to sweep their excess funds into an Investment Instrument. | G26: Yes
D27: Create Main Account and Set up Group Hierarchy (Notional Pooling) | E27: This process describes how accounts can be linked into a hierarchical structure of individual groups. Each group consists of a main account to which other (sub accounts) can be linked. | G27: Yes
D28: Create Sub Account (Notional Pooling) | E28: This process describes how each group consists of a main account to which other (sub accounts) can be linked. A main account in one group can be a sub account in another higher-level group. | G28: Yes
D29: Execute Intra-Day Sweep (Transactional Pooling) | E29: This process describes the execution of an intra-day sweep between customer accounts. The customer request is validated before performing an ad-hoc intra-day transfer. While performing intra-day sweep, cash pool suspend period is calculated and sweep is not executed if the day of sweep falls within cash pool suspend period. If float transfer is set to yes in the Group Param level, then on executing Intraday sweep, balances with future exposure dates (float) will be transferred from the sweep account to the main master account prior to executing the actual sweep. Sweep is executed based on the sweep type set in AC.CASH.POOL (Type: Surplus Sweep or Maintenance Sweep or Two-Way Sweep). | G29: Yes
D30: Execute Maintenance Sweep (Transactional Pooling) | E30: This process describes how a Maintenance sweep is performed. Maintenance Sweep is triggered while executing intra-day sweep by comparing the Sweep Account Balance of the cash pool with the Minimum Amount defined in the Cash Pool record. Credit happens to the sweep account considering the other aspects such as Minimum Transfer Credit, Sweep in units defined in the cash pool and Partial Transfer value defined in the Group Param level. Sweep will not happen if it does not meet the defined criteria in the cash pool. In case of multiple link accounts, Deficit in sweep account is swept as per the Link Account sequence defined in Rule Priority. | G30: Yes
D31: Execute Surplus Sweep (Transactional Pooling) | E31: This process describes how a Surplus sweep is performed. Surplus Sweep is triggered while executing intra-day sweep by comparing the Sweep Account Balance of the cash pool with the Maximum amount defined in the Cash Pool record. Debit to the sweep account happens considering the other aspects such as Minimum Transfer Debit, Maximum concentration Amount in link account, Sweep in Units defined in the cash pool and Partial Transfer value defined in the Group Param level. Sweep will not happen if it does not meet the defined criteria in the cash pool. In case of multiple link accounts, Surplus credit is executed as per the Link Account sequence defined in Rule Priority. | G31: Yes
D32: Execute Two Way type Sweep (Transactional Pooling) | E32: This process describes how a Two-Way sweep is performed. Two-Way sweep in general can be either Maintenance Sweep or Surplus sweep depending on the Sweep Account balance and Minimum/Maximum amount defined in the Cash Pool record. This process follows the same flow as defined in Maintenance/ Surplus Sweep once the Sweep type is identified. Sweep will not happen if it does not meet the defined criteria in the cash pool. For Two way sweep type, maintenance sweep condition is checked first and then the surplus sweep condition is checked. In case of multiple link accounts, Deficit in sweep account is swept as per the Link Account sequence defined in Rule Priority while Return Rule Priority sequence is considered for Surplus credit to Link Account. | G32: Yes
D33: Remove Sub Account from Notional Pooling | E33: This process describes how to remove a sub account from the group any time. | G33: Yes
D34: Reverse a Sweep Transaction (Transactional Pooling) | E34: This process describes the activities for revoking a sweep transaction already executed by the system. Reversal entries are passed during close of business. | G34: Yes
D35: Set Up or Amend Pool and Groups (Transactional Pooling) | E35: The group is created by specifying the master account. To the created group multiple accounts are linked to create the pool. This creates a tree structure of accounts held by a Corporate. The pooling could be either Shared or a Sweep. In case of Shared Pooling, the sum total of all account balances are checked while performing the transaction. For a Sweep setup, the balances are transferred according to defined rules. Cash Pool can be suspended - For a day by setting Suspend Start Date (or) - For a specific period by setting Suspend Start and Suspend End Date (or) - For an Indefinite period by setting Suspend Start Date and Suspend Indefinitely Sweep will not be performed between the accounts in the Cash Pool during Cash Pool suspension period. | G35: Yes
D36: Set Up Capitalisation Frequency and Credit Interest (Notional Pooling) | E36: This process describes how to setup capitalisation frequency and credit interest for accounts. | G36: Yes
D37: 2.1.4 Balance Netting - Cash Management
D38: 2.1.4.1 Manual Creation of Balance Netting Cash Pool
D39: Create Currency Summary (CS) or Summary Account (SA) | E39: This Process depicts the creation of Summary Account/ Currency Summary accounts which is part of the Cash Pool. Currency Summary account represents the sum of underlying Transaction Accounts of a Specific Currency. Summary Account represents the sum of underlying Transaction Account balances converted to the currency of the Summary Account. | G39: Yes
D40: Create Currency Top Account (CT) | E40: This Process depicts the initial process of Cash Pool i.e., creation of Currency Top Account. Currency Top Account represents the Company's outstanding balances per currency with the bank which is updated real-time with transactions from the Transaction Account in the same currency. Successful opening of the CT Account leads to associated sub processes viz., Creation of Master Account (MA), Currency Summary Account (CS)/ Summary Account(SA), Transaction (TR) Account to form the Cash Pool. | G40: Yes
D41: Create Master Account (MA) | E41: This Process depicts creation of Master Account as part of the Cash Pool. Master Account represents the customers total CT Account balances converted into Master Account currency which is updated real-time when there is an update in CT Account. The CT Account determines the currency of the Master Account and forms the Uppermost level in the Balance Netting Structure. | G41: Yes
D42: Create Transaction Account (TR) | E42: This Process depicts the creation of Transaction Accounts of the Cash Pool. Transaction Account is the Operational Account in the Cash Pool where transactions are booked with Real time transaction and balance updation. This can be denominated in any currency eligible. Relevant MA or SA/CS is mentioned in the creation process to form a complete cash pool. | G42: Yes
D43: 2.1.4.2 Automatic Creation of Balance Netting Cash Pool
D44: Activate Cash Pool and Pool Accounts | E44: This process details the steps for defining setting Cash Pool and Pool account Go Live date for a newly created Cash Pool. The Cash Pool and its Accounts will get activated on the SOD of their respective Go Live dates. | G44: Yes
D45: Create Cash Pool Accounts | E45: This process describes the steps involved in promoting a Cash Pool from Draft status to Preliminary status. Currency Top accounts, Summary accounts and Transaction accounts are created with account details in the placeholders created during draft status. Currency Top account is created for every currency of TR Accounts in the Cash pool. | G45: Yes
D46: Define Cash Pool Structure | E46: This Process describes the steps involved in defining Cash Pool structure. Cash Pool Master Account is created in Draft status and Pool accounts (SA, CS and TR) are created as placeholders. The actual creation of Pool accounts occurs when the Cash Pool is promoted to Preliminary status. | G46: Yes
D47: 2.1.4.3 Restructure of Cash Pool
D48: Activate Account in New Structure | E48: This process details the steps for setting Go Live date for a new or standalone account added to a Live pool. The new or standalone account in a live pool will get activated on the SOD of the Go Live date defined. | G48: Yes
D49: Add Standalone Account in Live Pool | E49: This process details the steps involved in adding customer's current account to customer Live pool. Newly added standalone account will act as the TR account of the Cash Pool. Standalone Accounts are added in Pending Live status to existing pool and will be activated on the Go Live date set for the accounts. | G49: Yes
D50: Change Cash Pool Structure | E50: This process details the steps for pool orchestration. Restructure of pool happens when one of the following activity happens in the pool. - Remove: TR Account in the Pool can be moved out as a Standalone Account. - Change Parent: TR/ MTR can be moved to a different parent in the same Pool. - Change Pool: TR or CS/ SA Account in one Pool can be moved to a different Live Pool. - Close: Close TR/ MTR Account from the pool on the date set. | G50: Yes
D51: Create New Account in Live Pool | E51: This process details the steps of adding new account to a Live pool. New Account can be included to the Pool either as TR/ MTR/ CS/ SA Account. New Accounts are created in Pending Live status in existing pool and will be activated on the Go Live date set for accounts. | G51: Yes
D52: 2.1.4.4 Balance Netting Transactions
D53: Execute Intra-Day Sweep Between Transaction Accounts | E53: This process describes the execution of an intra-day sweep between accounts of the pool. The customer request is validated before performing an ad-hoc intra-day transfer. While performing intra-day sweep, cash pool suspend period is calculated and sweep is not executed if the day of sweep falls within cash pool suspend period. Sweep will also check if the sweep time exceeds the master company time set in sweep order parameter. Sweep is executed based on the sweep type set in AC.CASH.POOL (Type: Surplus Sweep or Maintenance Sweep or Zero-Balancing Sweep). | G53: Yes
D54: Execute Maintenance Sweep Between Transaction Accounts | E54: This process describes the steps involved in performing a maintenance sweep. Maintenance Sweep is triggered while executing intra-day sweep by comparing the Sweep Account Balance of the cash pool with the Minimum Amount defined in the Cash Pool record. Credit happens to the sweep account considering the other aspects such as Minimum Transfer Credit set in the cash pool and cover control set in the sweep account. Sweep will not be performed if it does not meet the defined criteria in the cash pool. | G54: Yes
D55: Execute Surplus Sweep Between Transaction Accounts | E55: This process describes the steps involved in performing a surplus sweep. Surplus Sweep is triggered while executing intra-day sweep by comparing the Sweep Account Balance of the cash pool with the Maximum amount defined in the Cash Pool record. Debit to the sweep account happens considering the Minimum Transfer Debit defined in the cash pool. Sweep will not be performed if it does not meet the defined criteria in the cash pool. | G55: Yes
D56: Execute Zero Balance Sweep Between Transaction Accounts | E56: This process describes the steps involved in performing a Zero Balance sweep. Sweep is triggered to maintain account balance as Zero. Intra-day sweep will check the account balance and sweep out the surplus amount to link account. In case the account balance is less than Zero, the deficit is swept in from the link account after considering the cover limit set for the link account. | G56: Yes
D57: Initiate Funds Transfer Between Transaction Accounts | E57: This process describes the activities involved in initiating ad-hoc transfers between Transaction accounts within the same Bundle. | G57: Yes
D58: Set Up Standing Order Instructions between Transaction Accounts | E58: This process describes the activities involved in setting up of Standing Order instruction between Transaction accounts within the same Bundle for Internal Balance Netting transaction. | G58: Yes
D59: Set Up Sweep Between Transaction Accounts | E59: This process describes the activities involved in setting up an internal sweep between transaction accounts of the same bundle. User has to define values like Sweep Type, Frequency, Link Accounts to complete the set up. Sweep Types: Maintenance – Source account to maintain the minimum balance specified in sweep. Any deficit is swept from the link account. The deficit amount is debited from the link account and credited to the source account. Surplus - Source account to maintain the maximum balance specified in sweep. Excess balance is debited from the source account and credited to the link account. Zero Balancing – Source account to maintain zero balance. Any deficit is swept from the link account. The deficit amount is debited from the link account and credited to the source account. Excess funds is debited from the source account and credited to the link account. | G59: Yes
D60: 2.1.5 Account or Deposit Administration
D61: Amend Account (Corporate) | E61: This process describes the receipt of an amendment request for an account from the Customer and updating the same on the system. | G61: Yes
D62: Amend Deposit (LD) | E62: This process describes the receipt of an amendment request for a deposit from the Customer and updating the same on the system. | G62: Yes
D63: Block or Unblock Funds (Corporate) | E63: This Process describes blocking and unblocking of funds for an account, for a specific period or amount. Reservation of funds can be done either for an account or for all linked accounts in a balance netting pool based on Account Link. Account Link is set while defining locked event types in AC.LOCKED.EVENT.TYPE and the locked type used while blocking funds decides if reservation is done only for the transaction account (TR) in a balance netting pool or for all linked accounts. | G63: Yes
D64: Cancel Deposit (LD) | E64: This process describes the receipt of a cancellation request for a deposit from the Customer and updating the same on the system. | G64: Yes
D65: Change Account Statement Frequency (Corporate) | E65: This process begins with receipt of request from the Customer for change in the account statement frequency. After authentication of the request, the request is updated in the system. | G65: Yes
D66: Close Account (Corporate) | E66: The process begins with the receipt of an account closure request along with the unused deliverables (cheque book, debit card, etc.). The details are captured in the system and the closure activities are completed. The user has an option to pay the account closure proceeds in three modes, namely account transfer, teller and funds transfer. | G66: Yes
D67: Generate Account Statements (Corporate) | E67: This process describes handling of a customer request for an account statement (Current period/ Past period). | G67: Yes
D68: Manage Debit Card (Corporate) | E68: This process describes Debit card administration processes (cancellation/ return/ lost card reporting). | G68: Yes
D69: Perform Partial Withdrawals (LD) | E69: This process relates to partial withdrawal of a deposit through account transfer using "LD module". (This module does not allow for cash withdrawal.) | G69: Yes
D70: Perform Pre-Closure (LD) | E70: This process refers to premature closure of a deposit under "LD Module". | G70: Yes
D71: Reset Inactive Account (Corporate) | E71: This process describes the activities associated with changing the status of an account from inactive to active. | G71: Yes
D72: Revoke Stop Payment Of Cheque (Corporate) | E72: This process is used to revoke a stop payment of a cheque registered in the system. | G72: Yes
... D74: Stop Payment Of Cheque (Corporate) | E74: This process involves setting up a Stop payment for a cheque on receipt of a Customer request. | G74: Yes
C75: 2.2 Trade Finance and Guarantees | G75: =COUNTIF(G77:G186,"Yes") -> 93
D76: 2.2.1 Import Letter of Credit
D77: Accept Documents Under Import LC (Usance) | E77: The process covers activities in Acceptance of Usance LC documents. | G77: Yes
D78: Amend Import LC | E78: The process describes activities to perform internal or external amendments of Import LC. Certain external amendments would require beneficiary's consent. | G78: Yes
D79: Cancel Import LC | E79: Process describes activities for cancellation of Import LC. | G79: Yes
D80: Create Import Loan | E80: This process describes the activities for creation of Import Loan. Initially, the Import LC Bill is paid by creating an overdraft and subsequently funded through Import Loan. | G80: Yes
D81: Perform Discounting of Import LC | E81: The process covers activities to perform discounting of Usance LC Bill and remitting the funds to the exporter before maturity date of the Bill (after acceptance of the Bills by importer). | G81: Yes
D82: Accept or Reject Discrepant Documents Under Import LC (Sight) | E82: The process describes activities to be undertaken in case Sight LC documents are discrepant. Discrepant documents, can be accepted with the discrepancies and sent for settlement or rejected. Discrepant documents, upon a specific request from the Customer, can also be released on trust. | G82: Yes
D83: Accept or Reject Discrepant Documents Under Import LC (Usance) | E83: The process describes activities to be undertaken in case Usance LC documents are discrepant. Discrepant documents, can be accepted with the discrepancies, accepted with conditions or rejected. Discrepant documents, upon a specific request from the Customer, can also be released on trust. | G83: Yes
D84: Issue Back To Back LC | E84: The process describes activities to issue an Import LC against the security of Export LC. In these cases the applicant of the import LC and the beneficiary under the export LC would be the same entity. | G84: Yes
D85: Issue Import LC | E85: The process covers approval and issuance of Import LC. Various Types of LCs viz., Sight, Usance, Negotiation, Mixed Payment (part sight and part Usance), Standby LCs can be issued. | G85: Yes
D86: Lodge Documents Under Settled LC (Sight) | E86: This process describes lodgement of documents received under a settled LC sight bill. | G86: Yes
D87: Pre-Advise Import LC | E87: Process depicts capture and approve Pre Advise if required and send out MT705 to Correspondent Bank. Short particulars of LC are advised to the exporter's Bank through this process. | G87: Yes
D88: Receive Import LC Application | E88: Process depicts activities to receive & verify LC application, check if existing facilities are sufficient to fulfil request and forwarding the application to Back Office for processing. This process also covers an online input of LC details by the Customer through Online Channels and the subsequent submission of documents at the branch. | G88: Yes
... D96: Take or Release Margins | E96: This process describes the activities of Increase/ Decrease Margin on Import LC. | G96: Yes
D97: 2.2.2 Export Letter of Credit
D98: Accept and Liquidate Documents (Usance) | E98: Process depicts activities for recording the acceptance particulars of the Issuing Bank and liquidating the LC Bill on receipt of funds. | G98: Yes
D99: Advise Export LC | E99: The process describes activities to receive and advise the export LC established by the issuing Bank. LC may be advised to the customer directly or through another Bank. | G99: Yes
D100: Amend Export LC | E100: The process describes the activities to receive and advise Amendment of Export LC to the exporter. | G100: Yes
D101: Cancel Export LC | E101: The process describes the activities to receive and advise Cancellation of Export LC to the exporter. | G101: Yes
D102: Export Loan Adjustment | E102: The process describes the activities for repayment of export loan on receipt of export proceeds or funding by the exporter. | G102: Yes
D103: Liquidate Negotiated or Discounted Export LC (Sight or Usance or Mixed) | E103: The process describes activities for recording the acceptance from the Issuing Bank, for a bill negotiated under a Letter of Credit, and the subsequent liquidation of the Bill by the Negotiating Bank on receipt of funds in the Nostro account. | G103: Yes
D104: Liquidate Sight and Accept Usance Payment Under LC (Mixed) | E104: The process depicts activities when the sight portion of mixed LC Bills are realised by the LC issuing Bank/reimbursing Bank. Payment can also be made through Payment Order when export proceeds needs to be assigned to a the third party beneficiary, as assigned by the original beneficiary, through Nostro. | G104: Yes
D105: Liquidate Sight Payment Under LC (Sight) | E105: The process depicts activities when the sight LC Bills sent for collection are realised by the LC issuing Bank/reimbursing Bank. Payment can also be made through Payment Order when export proceeds needs to be assigned to a the third party beneficiary, as assigned by the original beneficiary, through Nostro. | G105: Yes
D106: Liquidate Negotiated or Discounted Export LC With Waived or Accepted Discrepancies | E106: The process describes the activities wherein the documents under LC which have been sent for acceptance/ collection (with discrepancies in documents) and subsequently discounted on receipt of acceptance. | G106: Yes
D107: Negotiate or Discount Export LC (Sight or Usance or Mixed) | E107: The Process describes activities to Negotiate/ discount export LC (Sight or Usance) documents with/ without discrepancies. | G107: Yes
D108: Perform Payment Under Reserve | E108: The process describes activities if the Sight Export documents under LC having discrepancies are negotiated under Reserve after accepting indemnity from the exporter. | G108: Yes
D109: Provide Export Financing | E109: The process depicts the activities to provide export packing credit or export loan if requested by the customer. | G109: Yes
... D113: Transfer Export LC | E113: The process depicts activities to transfer export LC on receipt of instructions from the 1st Beneficiary. | G113: Yes
...

Sheet (3) Transactional Processes
D2: Business Area | E2: Transactional Processes | G2: In Scope
D3: Total no. of processes | E3: =COUNTIF(E8:E635,"*") -> 496 | G3: =COUNTIF(G8:G636,"Yes") -> 496
D4: Release | E4: ='(2) Corporate Banking Processes'!E4 -> R25 Model Bank
G6: Scoping
B7: Process Area | C7: Scenario | D7: Process | E7: Process Description | G7: In Scope
B8: Transactional Processes
C9: 3.1 Payment Processes | G9: =COUNTIF(G10:G73,"Yes") -> 50
D10: 3.1.1 Drafts (Bankers Cheques)
D11: Manage Receipt Of Draft Stock | E11: This process describes activities performed by a front office Customer Service Officer on receipt of draft inventory from Head Office. | G11: Yes
D12: Perform Draft Encashment | E12: This Process describes the steps involved in settling local currency drafts across the counters by the teller. This can be achieved either by crediting the Customer's account with the bank or settlement by cash. | G12: Yes
D13: Process Cancellation Of Draft | E13: This process describes the steps involved in cancellation of LCY/ FCY draft. Once a confirmation is obtained that the draft is unpaid, for a LCY draft, immediate cancellation can be done, whilst in case of a FCY draft, the same is carried out upon receipt of confirmation of stop payment from the Nostro correspondent, on whom the FCY draft was issued. | G13: Yes
D14: Process Internal Draft Payments | E14: This process describes activities involved in processing internal draft. In an internal draft, the Initiator and Beneficiary will have accounts in the same bank. | G14: Yes
D15: Process Stop Payment Of Draft | E15: This process involves carrying out a stop payment of a draft. In case of a LCY draft, necessary status updates are carried out. For FCY drafts, stop payment confirmation is requested from the correspondent bank and response recorded and acted upon. | G15: Yes
D16: Receive and Process Request Of Stop Payment Of FCY Draft | E16: This process describes the steps involved in receiving and processing MT111 message. MT112 is generated and sent based on the status of the FCY draft. | G16: Yes
D17: Receive Request for Advice of Cheque | E17: This process describes the steps involved in receiving and capturing the details of MT110 (Advice of Cheque) which is used to advice the drawee bank, or confirm to an enquiring bank the details concerning the cheque referred to in the message. | G17: Yes
D18: Receive Request For Cancellation Of Draft | E18: This process deals with Customer giving a request for cancellation of a draft. The front office validates the request and forwards it to the back office for effecting the cancellation. | G18: Yes
D19: Receive Request For Revocation Of Stop Payment Of LCY Draft | E19: The process begins with the receipt of a revocation of stop payment request of a LCY draft. Necessary validations are carried out before forwarding the request to back office for processing. | G19: Yes
D20: Receive Request For Stop Payment Of Draft | E20: This process deals with Customer giving a request for stop payment of a draft. The front office validates the request and forwards it to the back office for effecting the stop payment. | G20: Yes
D21: Receive Request To Issue Draft | E21: The process is initiated on receipt of the draft/ bankers' cheque request by the front office. The request is then forwarded to the back office for further processing. | G21: Yes
D22: Revoke Stop Payment of LCY Draft | E22: This process describes activities associated with revocation of stop payment of a LCY draft. | G22: Yes
... D24: Reconcile Nostro Accounts * | E24: Periodically, Nostro accounts as in Bank's books will need to be reconciled with the account statement sent by the Nostro Bank. The statements may be received via SWIFT or physically and Transact automatically matches items and any unmatched items will need to be investigated. | G24: Yes
D25: 3.1.2 Standing Orders
D26: Cancel Standing Order Instruction | E26: This process describes the activities associated with the cancellation of a standing order instruction on receipt of a request from the customer. | G26: Yes
D27: Execute Standing Order | E27: This process is carried out for execution of the standing order. The payments orders are automatically generated using Standing order details. | G27: Yes
D28: Receive Request For Standing Order | E28: The process begins with the receipt of Standing order request from our Customers. Necessary verification is done before setting up the standing order. | G28: Yes
D29: Set Up Standing Order | E29: In this process, the standing order is set up based on the request of the customer. The request can be various types, viz. fixed amount transfer, maximum balance transfer, bulk standing order etc. | G29: Yes
D30: 3.1.3 Direct Debits
D31: 3.1.3.1 Direct Debits (Inward)
D32: Execute Direct Debit (Inward) | E32: The process describes the execution of the direct debit after a debit file is received from an originating bank. | G32: Yes
D33: Receive and Execute BACS Direct Debit (Inward) | E33: The process describes activities associated with the execution of an Inward Direct Debit. When claim file is received from Clearing, validations are performed. Upon successful validation, claims are honored, funds debited from Customer and accounting/ settlement entries raised. When validations fail, based on parameter setup, transactions are automatically cancelled or manually repaired/ cancelled. | G33: Yes
D34: Receive Request for Direct Debit E-Mandate (Inward) | E34: This process describes activities involved in the management of Direct Debit E-Mandates, which are registered and maintained electronically. Upon successful validation, the bulk file is debulked. Individual transactions are processed based on the request type received (pain.009-Register new mandate, pain.010-Amend existing mandate, pain.011-Cancel existing mandate). Corresponding error code and reason gets updated if validation fails. A response file is sent to centralized mandate system containing status of processed transactions. | G34: Yes
D35: Receive Request For Direct Debit Mandate (Inward) | E35: This process describes the validations that are undertaken on receipt of a customer's request for set up of an inward direct debit mandate. | G35: Yes
D36: Set Up Direct Debit Mandate (Inward) | E36: The process describes activities associated with registering an inward direct debit mandate in the system. | G36: Yes
D37: 3.1.3.2 Direct Debits (Outward)
D38: Cancel Direct Debit Instruction | E38: This process describes the activities associated with the cancellation of a Direct Debit mandate (Inward/ Outward). | G38: Yes
D39: Execute Cancellation of Outward Collection before Distribution to Clearing | E39: This process describes the steps involved in the cancellation of an outward Direct Debit collection request received via camt.055, API, etc. Post validation of the request, the cancellation request is accepted if payment/ collection is not sent to clearing. The cancellation request is rejected if the payment/ collection is already sent to clearing. Appropriate positive/ negative responses are sent via camt.029, pain.002 or API. | G39: Yes
D40: Execute Direct Debit (Outward) | E40: The process describes activities associated with the creation and execution of an outward direct debit mandate. On the claim date, system automatically generates and sends the Claim file to TPH. OFF-US the claim will be sent to clearing and Accounting/Settlement entries will be posted if claim is honored by debtor bank. ON-US Claims will be honored or returned to the customer based on direct debit validation. | G40: Yes
D41: Receive Request For Direct Debit (Outward) | E41: This process describes the validations that are undertaken on receipt of a customer's request for set up of an outward direct debit mandate. | G41: Yes
D42: Set Up Direct Debit Mandate (Outward) | E42: The process describes activities associated with registering an outward direct debit mandate in the system. | G42: Yes
D43: 3.1.4 Direct Credits
D44: 3.1.4.1 Direct Credit (Inward)
D45: Receive and Execute BACS Direct Credit (Inward) | E45: The process describes activities associated with receiving and executing a Direct Credit (Inward) file. Funds are credited to customer's account if BACS file validation is successful. On validation failure, based on parameter setup, Direct Credits received will either be automatically returned or placed in repair queue. A manual repair or return is possible for Direct Credits in repair queue. | G45: Yes
D46: Receive and Execute BACS Direct Credit Return (Inward) | E46: The process describes activities associated with processing Incoming return file from clearing. The return payment is matched with the original outward transaction and funds credited back to customer. When validation fails, transaction can be manually matched and customer credited. | G46: Yes
D47: 3.1.4.2 Direct Credit (Outward)
D48: Execute BACS Direct Credit Request (Outward) | E48: The process describes the generation of an outward Direct Credit. Based on customer request the customer account is debited and BACS file is generated and sent to clearing. | G48: Yes
D49: 3.1.5 Bulk payment
D50: Execute Funds Transfer Through Bulk Upload | E50: This process details the various types of credit payments to be effected on the processing date for a bulk upload viz., internal transfer, transfer to an external beneficiary through clearing/ SWIFT and payment through a Draft. | G50: Yes
D51: Perform Bulk Payment Validation | E51: This process deals with validations that will be performed upon successfully uploading a bulk payments file. On performing the validation of the Bulk Master, if errors are encountered the user can amend, cancel or reject the bulk items. On successful validation, User approves the master bulk records and then the bulk is released immediately for execution in the payment system. | G51: Yes
D52: Receive Bulk Payment Request | E52: This process highlights activities associated with the upload of a bulk file (credits or debits) by a Payment Officer received from the corporate customers. On successful upload the system creates master and individual records. | G52: Yes
D53: 3.1.6 Reconciliation
D54: Reconcile Nostro Accounts * | E54: Periodically, Nostro accounts as in Bank's books will need to be reconciled with the account statement sent by the Nostro Bank. The statements may be received via SWIFT or physically and Transact automatically matches items and any unmatched items will need to be investigated. | G54: Yes
D55: 3.1.7 Payment Order
D56: Amend Payment Order | E56: This process describes the activities of amending a payment order by a bank user. | G56: Yes
D57: Initiate Payment Order (Automatic) | E57: This process describes the steps involved in payment order initiation from different applications for payment related activities like Standing order execution, Loan disbursement etc. On initiation, Payment Order performs funds check and reserves the transaction amount for executing the payment. | G57: Yes
D58: Manage Payment Order Exceptions | E58: This process describes the steps involved in resubmitting/ cancelling Payment Orders in exception. Payment Order placed on hold can be rectified and resubmitted or cancelled. | G58: Yes
D59: Initiate Payment Order (Manual) | E59: The Payment Order application captures the payment instructions from the customer or from Channels or Bank internal processing and these orders are validated/ executed based on the Payment order parameter setup available for the Bank i.e. either through TPS or any 3rd party interfaces. | G59: Yes
D60: 3.1.8 Inward Entries
D61: Reverse Inward Entries | E61: This process describes the steps involved in reversing inward entries. Reversal will apply to a previously posted entry (individual AC.INWARD.ENTRY), irrespective of whether this has been processed via Single, Bulk or Batch processing mode. Once the entry is processed, the status of the Generic Accounting Request will be updated as either Fail/Success/Suspend depending on the Internal Accounting Request Mode (Field in AC.ENTRY.PARAM which specifies the accounting mode that should be used when the Generic Accounting message is generated, based on the manual request captured by the user) and the type of error/override raised during the reversal. | G61: Yes
D62: Set Up or Execute Inward Entries | E62: This process describes the execution of inward entries from customer bulk file. Based on OFS clearing mode, inward entries will be processed individually, as a batch or in bulk. Single entry processing (CSM): One entry/ request. The request message is processed online. Batch processing (CSMBATCH): multiple entry/ request. The batch message is received online, after the header is validated further processing is handled by a background process and the responses are asynchronous. The batch is split in individual messages which are the processed independently of each other. Bulk Processing (CSMBULK): multiple entry/ request. OFS Clearing will split the posting message in individual entries and will process them online in the sequence in which they are present in the request. Even if one entry fails the whole posting message is rejected. Process also describes the activity of Individual entries being matched against Transaction stop instructions during execution and in case of a match it is either returned or processed based on the default decision set in the parameter TZ.TRANSACTION.STOP.TYPE after creation of an investigation item (AC.FUNDS.AUTHORISATION on hold) | G62: Yes
D63: 3.1.9 Beneficiary
D64: Amend Beneficiary | E64: This process depicts activities associated with the amendment of a beneficiary. | G64: Yes
D65: Reverse Beneficiary | E65: This process depicts the activities involved in cancelling payee instructions. Payee instructions can be cancelled by reversing the beneficiary. If Validate beneficiary link is set to yes then an override is displayed when the beneficiary being reversed is used as a beneficiary in standing orders or future dated payment orders. | G65: Yes
D66: Set Up Beneficiary | E66: This process depicts activities associated with setting up beneficiary information - which in turn facilitates auto population of beneficiary details while performing transactions in FT module (account to account transfer and outgoing payments). | G66: Yes
D67: 3.1.10 Common Processes
D68: Perform Matching of Payment Notifications with Cover Payments | E68: This process describes matching of Payment Instructions with Cover Payments. The matching is automatically done when received before cut off time through SWIFT else manually matched. Exception Receipts record is created when Swift messages (MT202 COV, MT210, MT299, camt.057, pacs.009 cov and MT910) are received by the bank and is matched against the Payment messages like MT103, MT202, pacs.008 and pacs.009. | G68: Yes
D69: Perform Matching of GPI Cover Confirmation with Inward Remittance | E69: This process describes the activities of matching a payment message (MT103) against a GPI cover (MT299) received from GPI tracker. Expected receipts record is created when GPI cover MT299 is received by the bank and it is matched against the payment message MT103 depending on the matching conditions. If the matching is unsuccessful, then a notification (MT295) is triggered manually to other bank. | G69: Yes
D70: Set Up Transaction Stop | E70: This process describes the steps involved in setting up Transaction Stop instructions received from a Customer. During execution of Inward Entries and Account to Account Transfers, transactions will be validated against the Transaction Stop instructions. Before setting up Transaction Stop instruction, the below parameters needs to be set - Transaction Stop Parameter - parameterize Default Expiry Days, Days to History, Duplicate Stop Criteria at the lead company level. - Transaction Stop Types - define matching criteria for each Channel/Payment Type. This is defined at the lead company level and will apply to all the companies/branches under the lead. - Transaction Stop Condition - define stop conditions by indicating which attributes are allowed and for each attribute what are the allowed operands. - Transaction Stop Source Mapping Rules - define the transactions sources (OFS Clearing as well as FT) which are in scope of Transaction Stop Check and how the transaction details will be passed to the Transaction Check API. | G70: Yes
D71: Verify Direct Debit Transactions Limits | E71: This process represents system activities when a direct debit transaction is executed. | G71: Yes
D72: Verify Funds Transfer Transaction Limits | E72: Process depicts the system checks that are done while executing the funds transfer transaction limit. The Role based transaction limits, User group's authorization/ override management and Authorization levels are configured as part of the implementation requirement of the client Bank. The Model Bank system is configured for - 1 level of Authorization for majority of transactions (with exceptions such as 'Link collateral to limit' etc.). - The users rights are configured to accept overrides and input transactions without restrictions. | G72: Yes
D73: Verify Standing Order Transaction Limits | E73: This process depicts the system activities while executing a standing order. | G73: Yes
C74: 3.2 Cheque Collection and Clearing | G74: =COUNTIF(G75:G92,"Yes") -> 13
D75: 3.2.1 Internal Cheques
D76: Process Cheque Payment | E76: The process depicts the activities at the back office for processing the internal cheques. Necessary checks are done before processing the cheques. Cheque payment is done via Teller and cheque register is checked/ updated. | G76: Yes
D77: Receive Internal Cheque | E77: The process begins with the customer requesting a transfer from one account to another within the bank. The request may be dropped in a drop box or handed over to the teller in person. The request is forwarded to the back office for processing. | G77: Yes
D78: Verify Internal Cheque | E78: The process begins with the receipt of internal cheque at the back office for verification. The back office team ensures that the request is complete and all the checks are performed, before processing the transfer. | G78: Yes
D79: 3.2.2 External Cheques (Domestic)
D80: Process Cheque Clearing (Domestic) | E80: This process deals with activities associated with external domestic cheque clearing. The balances are released based on the cheque clearance status. For cheques that are returned, accounting entries are reversed, before returning the physical cheque to the Customer. | G80: Yes
D81: Receive External Cheque (Domestic) | E81: The process originates with the receipt of domestic external cheque (drawn on another bank) from the Customer, for collection into their account. The cheque may be deposited in person at the branches or dropped in a drop box. The branch forwards the cheque(s) to the back office for processing and clearing activities. | G81: Yes
D82: Verify External Cheque (Domestic) | E82: The cheques received from the branches are processed and presented for clearing. The bank sends the cheque for clearing through either Direct or Indirect method (depending upon the set up by Bank). | G82: Yes
D83: 3.2.3 External Cheques (Outstation)
D84: Process Cheque Clearing (Outstation) | E84: The process is to forward all the Outstation external cheques for collection. Based on the cheque clearance status the balances are released to the customer. If the cheque is returned then necessary accounting entries are passed and physical cheque is returned to the Customer. | G84: Yes
D85: Receive External Cheque (Outstation) | E85: The process originates with the receipt of Outstation external cheque (where the bank does not have a branch) from the Customer, for collection into their account. The cheque may be deposited in person at the branches or dropped in a drop box. The branch forwards the cheque(s) to the back office for processing & collection. | G85: Yes
D86: Verify External Cheque (Outstation) | E86: The process begins with the receipt of Outstation cheques at the back office for verification. The back office team ensures that the request is complete and all the details required for collection are available, before processing the cheques for collection. | G86: Yes
D87: 3.2.4 External Cheques (Foreign Currency)
D88: Process External Cheque (FCY) | E88: The process identifies activities associated with the settlement of the foreign currency cheque. Based on the cheque clearance status, identified from the Nostro statement, the balances are released/ returned. | G88: Yes
D89: Receive External Cheque (FCY) | E89: The process describes the activities for accepting a foreign currency cheque from the Customer (either through the branch counter or through the drop box) and making the cheque available to back office for processing. | G89: Yes
D90: Verify External Cheque (FCY) | E90: Process describes the activities for verifying the details of cheques presented for collection, capturing the details of foreign currency cheque, and authorisation of the cheque deposited. | G90: Yes
D91: 3.2.5 Cheque Administration
D92: Modify Cheque Settlement Date | E92: This process deals with activities associated with changing the value date of cheque clearing, on account of any unforeseen events (sudden declaration of holiday by clearing house etc.). | G92: Yes
C93: 3.3 Payment Hub | G93: =COUNTIF(G95:G187,"Yes") -> 85
D94: 3.3.1 SWIFT Transfers
D95: Execute Call Back - Cancellation of Credit Transfer through GPI tracker (PP) | E95: The process describes the activities involved in processing the cancellation of outward remittance for GPI enabled bank. Based on the confirmation received, the cancellation request is processed and customer is informed. If the recall is accepted, the customer is credited after sighting the credit in the bank's Nostro account. | G95: Yes
D96: Execute Call Back - Cancellation of Credit Transfer (PP) | E96: The process describes the activities involved in processing of cancellation/ call back of outward remittance for Non-GPI enabled banks at the back office. The cancellation will be taken up after sighting the credit in the bank's Nostro account. Based on the confirmation received, the cancellation request is processed. If the recall is accepted, the customer is credited back else, the customer is informed on the recall rejection. | G96: Yes
D97: Execute Claim Received for Outward Remittance (PP) | E97: This process describes the steps involved in receiving a claim request (camt.106 or MT191) for an outgoing credit transfer (103, 103+, 102, 102+, pacs.008, pacs.009) with OUR/ SHA charges (to collect the deficit charges from ordering customer). Post validation, the claim request is ignored, a payment is initiated through Book Transfer or Bank Transfer to settle the claim request. | G97: Yes
D98: Process Cancellation Request of Outward Remittance (PP) | E98: This process describes the activities involved in the cancellation of an outward credit transfer received via camt.055, API, etc. Post validation of the request, the cancellation request is accepted if the transaction is not completed or if the Intermediary/ beneficiary bank is not credited manually or automatically. Further, a cancellation request is generated as camt.056 to the clearing/ intermediary bank if funds are credited to the Intermediary/ beneficiary bank. Appropriate positive/negative responses for camt.056 are received via pacs.004 or pacs.002 along with camt.029. Customers are informed via camt.029, pain.002 or API. | G98: Yes
D99: Execute Inward Cancellation Request through GPI tracker (PP) | E99: This process describes the activities involved in receiving a recall request (camt.056) by GPI tracker for an inward remittance. Appropriate positive/ negative responses for camt.056 are sent via pacs.004/ pacs.002 and camt.029. Customers are further informed of the responses sent via pain.002 or API. | G99: Yes
D100: Initiate Outward Cancellation Request through GPI Tracker (PP) | E100: This process describes the activities involved in initiating a recall request (camt.056) sent through the GPI tracker for outward remittance. The recall request is initiated after checking the acceptance period. Appropriate positive/ negative responses for camt.056 are received via pacs.004/ pacs.002 and camt.029. Customers are further informed of the responses received via CAMT.029, pain.002 or API. | G100: Yes
D101: Initiate Outward Cancellation Request for Customer Transfer (PP) | E101: This process describes the activities involved in initiating a recall request (camt.056) of outward remittance by a Customer. The recall request is initiated post checking of the acceptance period. Based on the response received, the recall request is accepted or rejected. | G101: Yes
D102: Initiate Outward Cancellation Request for Bank Transfer (PP) | E102: This process describes the activities involved in initiating a recall request (camt.056 and camt.058) for outward remittance sent by a Bank. The recall request is initiated post checking of the acceptance period. Based on the response received, the recall request is accepted or rejected. | G102: Yes
D103: Process Reversal or Cancellation of Inward Remittance (XML) (PP) | E103: This process describes the activities involved in receiving a recall request (camt.056) of inward remittance. When the request is received, the status of the original payment is validated. Based on the status of the payment, the recall request is accepted or rejected and a response is sent via pacs.002, pacs.004 or camt.029. | G103: Yes
...

Sheet (4) Treasury Processes
D2: Business Area | E2: Treasury | G2: In Scope
D3: Total no. of processes | E3: =COUNTIF(E8:E142,"*") -> 79 | G3: =COUNTIF(G8:G142,"Yes") -> 79
D4: Release | E4: ='(3) Transactional Processes'!E4 -> R25 Model Bank
G6: Scoping
B7: Process Area | C7: Scenario | D7: Process | E7: Process Description | G7: In Scope
B8: Treasury Processes
C9: 4.1 Derivatives (Own book) | G9: =COUNTIF(G11:G22,"Yes") -> 9
D10: 4.1.1 Position and Market Analysis
D11: Perform Position and Market Analysis (Derivatives or Own Book) | E11: As part of this process, current position and market information is analysed and an appropriate trading strategy for derivatives (own book) is formulated. | G11: Yes
D12: 4.1.2 Trade Initiation
D13: Execute Trade (Derivatives or Own Book) | E13: This process describes the capture of an Own book or a Customer derivatives deal in the system. In own book it's a direct trade input and for Customers the trade can be originated through an order as well. | G13: Yes
D14: 4.1.3 Settlement
D15: Execute Settlement (Derivatives or Own Book) | E15: Once a Derivatives Trade (Own Book) is completed and verified, system automatically generates accounting entries and Trade confirmation advices. | G15: Yes
D16: 4.1.4 Administration
D17: Create Derivatives Exchange Master * | E17: This process covers the creation of a derivatives exchange master. The details of the exchange/ market like description, address and the margins are captured here. | G17: Yes
D18: Create Derivatives Master * | E18: This process describes the activities involved in creation of a derivatives master for all instruments (futures, stocks or options) that is traded in the exchange. An Asian or non Asian derivative master is created based on option style of the instrument. | G18: Yes
D19: Exercise Option or Assignment (OTC) | E19: The process is triggered over the counter (OTC), when the customer requests for exercising the option or where counterparty requests for an assignment. The option is exercised/ assigned and system creates a closeout record. On committing the closeout record, system creates Forex trade. System can also be parameterised to automatically exercise an Option if pre-defined conditions are met. | G19: Yes
D20: Manage Maturity or Expiry (Derivatives or Own Book) | E20: On maturity of futures contract or expiry of options contract, system would automatically mark the record as 'expire'. This process is for manually capturing the maturity of a futures contract or the expiry of an option contract. | G20: Yes
D21: Perform Closeout (Derivatives or Own Book) | E21: Comparable Buy and Sell Trades can be closed out either manually by specifying selection criteria or automatically by the System (if so parameterised). A close out record is created and upon authorisation, system automatically closes out the positions and generates the accounting entries. | G21: Yes
D22: Trigger Exotic Options (Derivatives or Own Book) | E22: For exotic options, if the Trigger is reached, this has to be manually input in Transact. E.g. for a Knockout option, when the knockout price is reached, Investment representative will have to input that the option is triggered. Once triggered, the option will automatically become live or expire as the case maybe. | G22: Yes
C23: 4.2 Securities (Own book) | G23: =COUNTIF(G25:G37,"Yes") -> 10
D24: 4.2.1 Position and Market Analysis
D25: Perform Position and Market Analysis (SEC or Own Book) | E25: This process describes analysing the position, outstanding orders and market data to formulate trading strategy. | G25: Yes
D26: 4.2.2 Trading Initiation and Execution
D27: Execute Trade (Sec or Own Book) | E27: This process describes execution of a trade (Sec/ Own book). The trade details are captured in the system where automatic validation vis-à-vis validation of trade data for stock and cash availability, restrictions, etc., is carried out. | G27: Yes
D28: Generate Advices and Perform Pre Matching (Sec or Own Book) | E28: The process describes authorising of security trades for proprietary (own book) portfolios. After trade authorisation, system will post accounting entries and advices to Broker & Custodian will be generated. | G28: Yes
D29: 4.2.3 Settlement
D30: Execute Settlement (Sec or Own Book) | E30: This process describes settlement of a trade (Sec/Own book). On trade authorization and once the advices and pre-matching is complete, system automatically checks for the type of settlement to be performed (actual vs contractual). On receipt of appropriate settlement confirmation from the depository/ custodian, trade is “settled” with the updation of cash and security positions. | G30: Yes
D31: Perform Dealer Book Portfolio Transfer | E31: Process describes the transfer of assets between dealer book portfolios. The positions are defined and transfer details are captured/ updated. | G31: Yes
D32: Perform Off-Market Trade or Transfers (Own Book) | E32: This process describes the activities relating to capture of data for off-market transfer in/ out of Proprietary (own book) portfolios. | G32: Yes
D33: 4.2.4 Administration
D34: Create Security Master * | E34: The process describes capturing of new securities into the master for future trading. | G34: Yes
D35: Maintain Security Prices * | E35: The security prices are updated into the tables through external system's interface or manually updated. | G35: Yes
D36: Set Up Broker * | E36: Broker is opened as a Customer in Transact. As part of this process, data relating to securities, Account creation (if required) and settlement instructions are captured. | G36: Yes
D37: Set Up Depository * | E37: Depository or Custodian is opened as a Customer in Transact. As part of this process, data relating to the custodian's Securities, Nostro accounts and SWIFT address are updated. | G37: Yes
C38: 4.3 FRA | G38: =COUNTIF(G39:G47,"Yes") -> 5
D39: 4.3.1 Position and Market Analysis
D40: Perform Position and Market Analysis (FRA) | E40: This process involves formulation of an appropriate FRA deal strategy after analysis of current position and market information. | G40: Yes
D41: 4.3.2 Trading Initiation and Execution
D42: Execute Trade (FRA) | E42: The process describes capturing FRA trade information details and providing trade data to back office for further processing. Details of Legal Entity details with their status and Expiry date is captured in LE.DIRECTORY. The logic to identify transactions that are in scope of MIFID II is defined in LE.ELIGIBILITY.PARAM. System enables the LEI/NCI checks for those qualifying transactions with Override/Error check. Legal Entity ID/ National Client ID is captured while creating OC.CUSTOMER. While executing a Trade, the LEI check is initiated during transaction commit and override/error triggered where LEI or NCI for the parties to the transaction are not available or conditions not being met. | G42: Yes
D43: 4.3.3 Confirmation
D44: Complete Trade Data and Confirmation (FRA) | E44: This process involves verification of FRA deal details, settlements, authorisation and confirmation of FRA. | G44: Yes
D45: 4.3.4 Settlement
D46: Fix Rates (FRA) | E46: This process involves contacting the counterparty and fixing the FRA settlement interest rate. | G46: Yes
D47: Execute Settlement (FRA) | E47: This process describes the Settlement of FRA deals and generation of settlement messages. | G47: Yes
C48: 4.4 SWAPS | G48: =COUNTIF(G49:G57,"Yes") -> 5
D49: 4.4.1 Position and Market Analysis
D50: Perform Position and Market Analysis (SWAP) | E50: This process involves formulation of an appropriate SWAP deal strategy after analysis of current position and market information. | G50: Yes
D51: 4.4.2 Trading Initiation and Execution
D52: Execute Trade (SWAP) | E52: This process describes the capturing of SWAP deal data in the system and providing trade data to back office for further processing. Details of Legal Entity details with their status and Expiry date is captured in LE.DIRECTORY. The logic to identify transactions that are in scope of MIFID II is defined in LE.ELIGIBILITY.PARAM. System enables the LEI/NCI checks for those qualifying transactions with Override/Error check. Legal Entity ID/ National Client ID is captured while creating OC.CUSTOMER. While executing a Trade, the LEI check is initiated during transaction commit and override/error triggered where LEI or NCI for the parties to the transaction are not available or conditions not being met. | G52: Yes
D53: 4.4.3 Confirmation
D54: Complete Trade Data and Confirmation (SWAP) | E54: This process involves verification of SWAP deal details, settlements details, authorisation and confirmation of SWAP. | G54: Yes
D55: 4.4.4 Settlement
D56: Execute Settlement (SWAP) | E56: This process describes the settlement of SWAP deals, posting of accounting entries and generation of SWIFT messages. | G56: Yes
D57: Reset Rates (SWAP) | E57: This process involves contacting the counter party for periodic interest rate setting. The system automatically generates SWIFT message confirming the rate change. | G57: Yes
C58: 4.5 Money Market | G58: =COUNTIF(G59:G67,"Yes") -> 5
D59: 4.5.1 Position and Market Analysis
D60: Perform Position and Market Analysis (Money Market) | E60: This process involves formulation of an appropriate MM deal strategy after analysis of current position and market information. | G60: Yes
D61: 4.5.2 Trading Initiation and Execution
D62: Execute Trade (Money Market) | E62: This process describes the capture of a MM deal in the system and providing trade data to back office for further processing. | G62: Yes
D63: 4.5.3 Confirmation
D64: Complete Trade Data and Confirmation (Money Market) | E64: This process describes the activities associated with verification of all the details of a MM deal - viz., authorisation, settlement and matching trade confirmation with deal data. | G64: Yes
D65: 4.5.4 Settlement
D66: Execute Settlement (Money Market) | E66: This process describes the settlement of MM call/notice deals, where a settlement date has to be input. Once the settlement date is entered, the posting of accounting entries and generation of SWIFT messages is an automated activity. | G66: Yes
D67: Process Rollover or Repayments (Money Market) | E67: This process details the maturity repayment or rollover of a money market deal. The system automatically generates the accounting entries and applicable SWIFT messages. | G67: Yes
C68: 4.6 Forex | G68: =COUNTIF(G70:G86,"Yes") -> 12
D69: 4.6.1 Position and Market Analysis
D70: Perform Position and Market Analysis (Forex) | E70: This process involves formulation of an appropriate Forex deal strategy after analysis of current position and market information. | G70: Yes
D71: 4.6.2 Trading Initiation and Execution
D72: Execute Forex Trade (Bulk Order) | E72: The process describes capturing bulk Forex deals information. The bulk order creates an order (in FX.ORDER) on authorisation. | G72: Yes
D73: Execute Internal Forex Deal | E73: This process describes the transfer of positions between dealers. | G73: Yes
D74: Execute Trade (Forex) | E74: This process describes capturing of a Forex deal in the system and providing trade data to back office for further processing. Details of Legal Entity details with their status and Expiry date is captured in LE.DIRECTORY. The logic to identify transactions that are in scope of MIFID II is defined in LE.ELIGIBILITY.PARAM. System enables the LEI/NCI checks for those qualifying transactions with Override/Error check. Legal Entity ID/ National Client ID is captured while creating OC.CUSTOMER. While executing a Trade, the LEI check is initiated during transaction commit and override/error triggered where LEI or NCI for the parties to the transaction are not available or conditions not being met. | G74: Yes
D75: Receive and Initiate FX Limit Order | E75: A Limit Order, is an order to close a trade when the market moves to a specified amount to the advantage of a position. This process describes the activities associated with receipt and initiation of FX limit orders. | G75: Yes
D76: 4.6.3 Confirmation
D77: Verify Trade Data and Confirmation (Forex Bulk Order) | E77: When the trade data is available to the back office, a master deal is generated to capture the bulk order. Upon authorising the master deal, the child deals are created. | G77: Yes
D78: Verify Trade Data and Confirmation (Forex) | E78: This process involves verification of Forex deal details, settlements, authorisation and matching trade confirmation with deal data. | G78: Yes
D79: 4.6.4 Post-Trade Events
D80: Execute Cancellation (Forex) | E80: This process describes the activities involved in cancelling an existing Deal either partially or fully and sending cancellation details to back office supervisor for review and authorisation. Post authorisation, an confirmation advice is sent to counterparty. | G80: Yes
D81: Execute Delivery (Forex) | E81: This process describes the activities involved In capturing an early partial or full delivery (settlement) of a Forex option Deal. Settlement details such as the settlement amount buy or sell, settlement account, settlement currency is captured. Post authorisation, an confirmation advice is sent to counterparty. | G81: Yes
D82: Execute Rollover (Forex) | E82: This process describes the activities involved in rollover of an existing Deal either partially or fully. Existing deal is cancelled and a new Deal created subsequently. Cancellation details is sent to back office supervisor for review and authorisation. Post authorisation, an confirmation advice is sent to counterparty. | G82: Yes
D83: 4.6.5 Settlement
D84: Execute Settlement (Forex) | E84: This process describes the settlement of Forex deals, posting of accounting entries and generation of SWIFT messages. | G84: Yes
D85: 4.6.6 Rate Quotation
D86: Process Internal Rate Request (Forex) | E86: This process describes the dealer activity of providing the FX rates (Execution Rate) for Lim order deals requested internally. | G86: Yes
C87: 4.7 Non-Deliverable Forward | G87: =COUNTIF(G88:G95,"Yes") -> 4
D88: 4.7.1 Position and Market Analysis
D89: Perform Position and Market Analysis (NDF) | E89: This process involves formulation of an appropriate Non-deliverable Forward Deal strategy after analysis of Current position and market information. | G89: Yes
D90: 4.7.2 Trading Initiation and Execution
D91: Execute Non-deliverable Forward Trade (NDF) | E91: This process describes capturing of Non-deliverable Forward trade information details in Front Office and providing Trade data to back office for further processing. | G91: Yes
D92: 4.7.3 Confirmation
D93: Verify Trade Data and Confirmation (Forex) * | E93: This process involves verification of Forex deal details, settlements, authorisation and matching trade confirmation with deal data. | G93: Yes
D94: 4.7.4 Settlement
D95: Execute Settlement (NDF) | E95: This process describes the settlement of an NDF deal by applying the settlement rate (on the rate fixing date) and arriving at the difference between notional amount and settlement amount. | G95: Yes
C96: 4.8 Repo or Reso | G96: =COUNTIF(G97:G107,"Yes") -> 7
D97: 4.8.1 Position and Market Analysis
D98: Perform Position and Market Analysis (REPO or RESO) | E98: This process involves formulation of an appropriate REPO/ RESO deal strategy after analysis of current position and market information. | G98: Yes
D99: 4.8.2 Trading Execution
D100: Amend Deal (REPO or RESO) | E100: This process highlights the amendments carried out to a REPO/RESO deal. | G100: Yes
D101: Manage Stock Borrow Lending * | E101: This process explains the amendment of existing SBL Transactions that are not liquidated. System supports substitution of securities and also allows user to amend the maturity date of existing SBL transactions. | G101: Yes
D102: Execute Trade (REPO or RESO) | E102: This process describes capturing a REPO/RESO deal in the system and providing trade data to the back office for further processing. Floating rate Repos can be input by linking the Periodic Interest table to a Repo contract for CLASSIC type of Repo contracts. Intra-day Repos can be input by setting the INTRADAY.TRADE to YES, providing the Start and End Time of the contract. The system calculates the interest amount for the duration between the start and end time and the contract matures on the same day. | G102: Yes
...

Sheet (5) Private Wealth Management
D2: Business Area | E2: Private Wealth Management | G2: In Scope
D3: Total no. of processes | E3: =COUNTIF(E8:E399,"*") -> 319 | G3: =COUNTIF(G8:G399,"Yes") -> 319
D4: Release | E4: ='(4) Treasury Processes'!E4 -> R25 Model Bank
G6: Scoping
B7: Process Area | C7: Scenario | D7: Process | E7: Process Description | G7: In Scope
B8: Private Wealth Management Processes | C8: 5.1 Asset Management
C9: 5.1.1 Discretionary Asset Management | G9: =COUNTIF(G11:G41,"Yes") -> 22
D10: 5.1.1.1 Investment Policy Definition
D11: Define Asset Allocation | E11: Asset allocation is a term used to refer to how an investor distributes his or her investments among various classes of investment vehicles. This Process describes defining asset allocation based on various parameters like investment strategy, regulatory restrictions etc. | G11: Yes
D12: 5.1.1.2 Constraints and Restrictions Definition
D13: Maintain Security Recommendation | E13: The recommended list of securities is provided by investment analyst. Recommendations can be maintained in Transact and will be considered e.g. for Rebalancing, … | G13: Yes
D14: Perform Pre Trade and Post Trade Restrictions | E14: Process to setup various holding and transaction restrictions from inputs obtained from regulatory or compliance authorities, analysts etc. | G14: Yes
D15: Set Up Global Constraints | E15: Process to set up regulatory and institutional constraints. A Global constraint could be restriction for trades in certain countries, stocks, … | G15: Yes
D16: 5.1.1.3 Portfolio Modeling
D17: Assign Model To Investment Strategy | E17: This process describes the assignment of a portfolio model to an investment strategy. | G17: Yes
D18: Create Dynamic Model | E18: A dynamic model is created for a virtual customer. This model can then be used as the 'model' portfolio for modelling and rebalancing client portfolios. | G18: Yes
D19: Create Model From Portfolio | E19: An investment strategy or Model is created from an existing client Portfolio (or Dynamic Portfolio). The process describes selection of a Portfolio, based on which Strategy is defined. The system will generate the Strategy (Model) which is then linked to the Investment Strategy file and used to rebalance existing portfolios. | G19: Yes
D20: Maintain Cash Model | E20: A Cash Model or Strategy is created. This is linked to the Investment Strategy file which is then used to rebalance the currency positions of existing portfolios. | G20: Yes
D21: Maintain Securities Model | E21: This process describes maintenance of a Securities Model, e.g. pure equity, balanced, etc. This is linked to the Investment Strategy file so that it can be used to rebalance the securities positions of existing portfolios. | G21: Yes
D22: 5.1.1.4 Comparison and Rebalancing
D23: Perform Currency Rebalancing | E23: Selected Portfolios are compared with a pre-defined Currency Strategy. On running the Comparison, system will generate a list of Portfolios that are in deviation. A rebalancing is then run (the system generates Forex spot trades to balance) to bring the currency positions in sync with the Strategy. | G23: Yes
D24: Perform Group Rebalancing | E24: It is possible to set a Strategy at Group Level and rebalance the group as a whole. An Order of Priority in which the Portfolios in the group are to be rebalanced can be set. Tax Portfolios can have their own Strategy and system would rebalance any Tax Portfolios using their individual strategies, and then ensure that the Group is rebalanced overall to align with the Group Strategy. Proposed orders can be accepted or rejected with a Reason. It is also possible to Raise a certain amount of Cash from a Group of Portfolios, while maintaining the Strategy. If a Portfolio is part of a Rebalancing group, it cannot be rebalanced individually. | G24: Yes
D25: Perform Security Rebalancing | E25: Selected Portfolios are compared with a pre-defined Securities Strategy. On running the Comparison, system will generate a list of Portfolios that are in deviation. A rebalancing is then run to bring the Securities Position in sync with the Strategy. | G25: Yes
D26: Perform What-If Scenario Analysis | E26: The portfolios are selected for what-if analysis and simulations are performed on the portfolios. This will help determine the scenarios in which a rebalancing may be required. | G26: Yes
D27: 5.1.1.5 Order Management
D28: Perform Bulk Order - Normal | E28: This process allows manual rebalancing of Securities Positions of Portfolios. Portfolios which satisfy the selection criteria are rebalanced in one go. For securities that can be bought or sold or switched, the system creates a list of proposed orders and upon accepting the same, security orders are created to rebalance the portfolios. | G28: Yes
D29: Perform Bulk Order (Service Run) | E29: Service based Bulk Orders can be generated for Purchase, Sale and Multiple Switching of securities, through services running at the background. Specific selection criteria has to be specified should be based on the PERCENTAGE and NOMINAL fields, which will be executed on the selected Portfolios and generate the Orders. In the orders generated through SERVICE, the customer details will exist as individual transactions and it will be possible to amend the customer nominals in this application. Here, Auto Select field is set to SERVICE, system will generate/re-generate portfolios with suggested nominals to complete the order. The orders thus generated, has to be executed similar to that of normal Sec Open Orders. | G29: Yes
D30: 5.1.1.6 Back value Processing
D31: Perform Back Value Processing | E31: Portfolio Positions will change when there are back valued transactions. This could be a back valued trade or transaction for the portfolio or a back dated Security price change or back dated exchange rate change. System can be parameterised to automatically update Cash or Security positions when back valued transactions occur and recalculate the performance. | G31: Yes
D32: 5.1.1.7 Performance
D33: Maintain Benchmarks For Performance Reporting | E33: Portfolio performances can be compared to a defined Benchmark. To do this, a Benchmark is defined and then linked to a Portfolio. | G33: Yes
D34: Maintain Composites For Performance Reporting | E34: Composite Portfolio Performances can be displayed and reported in Transact. A composite name has to be defined and Portfolios with similar investment strategies can be plugged to the composite. It is possible to define Composites to comply with GIPS standards. | G34: Yes
D35: Maintain Group Of Portfolios | E35: Portfolios that are in some way related to each other, can be grouped in order to study Performance for the group as a whole. These Transact functions do not require an authorisation. | G35: Yes
D36: 5.1.1.8 Segmentation
D37: Define Portfolio Segmentation | E37: Portfolio Valuation can be viewed as a break-up of different segments. Segments need to be defined and while viewing the valuation, a segment ID can be given to display the details accordingly. | G37: Yes
D38: 5.1.1.9 Hierarchical valuation
D39: Set Up Asset Structures | E39: Portfolio valuation can be viewed in different ways by setting up suitable Hierarchy structures and using them while launching the valuation enquiries. | G39: Yes
D40: 5.1.1.10 Sweep
D41: Execute Sweep (Asset Management) | E41: This process depicts the various ways in which the funds available in the form of securities, shares, positions, accounts, etc. are swept and credited to the customer. | G41: Yes
C42: 5.2 Trading
C43: 5.2.1 Securities | G43: =COUNTIF(G46:G138,"Yes") -> 82
D44: 5.2.1.1 Trading Initiation and Execution
D45: 5.2.1.1.1 Common Order Placement
D46: Receive and Initiate Common Order Placement | E46: This process enables the RM to view the products under PWM & input the order at the front office by capturing the details in a progressive manner. The assumption is that the customer is authenticated and balance checked before inputting the common order placement. The process then leads to capturing further details. The orders can be placed for initiating security order (STP), security order (1step), derivatives order, fiduciary order, forex trade, money market trade, mutual fund order etc. | G46: Yes
D47: 5.2.1.1.2 Miscellaneous Orders
D48: Initiate Structured Note Trade | E48: System supports handling various structured notes. Additional fields are available added in Security Master to capture the details/ terms of these products (underlying security/basket of securities, strike price, barriers, fixing date, etc.). These instruments will be traded using the securities module. All the events during the life cycle of these products (KIKOs, fixing, pay-out details) will be received from the Issuer (from upstream systems through interface). | G48: Yes
D49: Manage In-house Orders | E49: This process indicates the activities involved in case the Customer places a request with Transact bank for execution of trades for securities held outside the system i.e. securities maintained with the custodian other than the Transact Bank. Such trade request are processed through in-house orders. Appropriate SWIFT messages and confirmations are sent to Customer, custodian and brokers. | G49: Yes
D50: Manage Third Party Custody Orders | E50: Transactions executed by the Customer in portfolio outside Transact Bank can be captured using third party orders process. | G50: Yes
D51: Manage Third Party Custody Trades | E51: After the third party custody orders are captured, the trades are captured in Transact using third party custody trades process. | G51: Yes
D52: 5.2.1.1.3 Private Equity
D53: Initiate Capital Call for Private Equity | E53: This process describes the steps involved in initiating the Capital Call for the related Private Equity Investment. The capital call notice from the issuer can be a regular capital call after the initial commitment or an equalization call after the late commitment. The capital call can be initiated with an amount or as a percentage on the commitment amount. On receipt of Capital Call/ Equalization call notice from the Issuer of the PE Fund, the system updates the event amount and other fee details for each investor of PE Fund, which then updates the position against the PE fund for the respective investors. | G53: Yes
D54: Initiate Capital Return (PE) | E54: This process describes the steps involved in handling Capital return of Private Equity Investment. “Return of Capital Call” notice will be issued by a Private Equity firm when a suitable investment opportunity is not established for the Capital call initiated previously. On receipt of “Return of Capital Call” notice, customer's undrawn commitment amount is updated and customer's account credited with the capital returned amount along with interest and fees (if any). | G54: Yes
D55: Initiate Commitment Reduction (PE) | E55: This process describes the step involved in handling of “Commitment Reduction" in Private Equity investment. Based on the commitment reduction percentage, Customers' position against Committed Capital and Undrawn Commitment is reduced. | G55: Yes
D56: Initiate Private Equity Investment | E56: This process describes the steps involved in capturing details of initial and late commitment by a customer to a Private Equity Fund and the commitment subsequently being formalised. Formalizing the commitment can be done at the product events level as well. The formalised commitment is usually invested over time as investments are identified. When the commitments are formalised, the system updates the Security Position for the customer against this PE instrument. | G56: Yes
D57: Initiate Private Equity Maturity | E57: This process describes the step involved in handling Maturity of Private Equity Investment. When the Maturity event is processed, each customer is credited with the final maturity amount based on the maturity price of the PE fund. | G57: Yes
D58: Initiate Recallable Return of Capital | E58: This process describes the steps involved in handling the recallable return of capital in Private Equity. Recallable Capital is an event where the capital distributed can be called back for investment in the PE fund. The recallable portion of the capital can be equal to or less than the capital returned. On receipt of the "Recallable capital" notice, the customer's undrawn commitment amount is increased accordingly. | G58: Yes
D59: Process Management Fees (PE) | E59: This process describes the step involved in processing Management Fees for the respective PE investment. Management Fees are charged against the commitment of each investor for given percentage and frequency. Once calculated, the Fees can be amended for each Investors before the same is credited to the Issuer Account. | G59: Yes
D60: 5.2.1.1.4 Securities Orders
D61: Amend or Cancel Order | E61: The process describes the activities of Order Amendment/ Cancellation prior to execution. | G61: Yes
D62: Complete and Authorise Trade (Manual) | E62: On execution of a Securities Order, a Trade is created in the system. The Trade needs to be completed and authorised. Subsequently, if required, allocation instructions can be maintained manually. Completion and Authorisation of parent trade will automatically authorise child trades. | G62: Yes
D63: Complete and Authorise Brokerage Only Transactions | E63: This process describes the activities where a bank can act as broker only for transactions in specific portfolios. On execution confirmation from the external broker, system will create two trades. The first trade (Trade 1) will be between the customer and the bank, where bank acts as an intermediate broker and a second trade (Trade 2) between bank and the external broker, where bank acts an intermediate customer. MT541/ MT543/ sese.023 (MX message) is sent to settle a transaction with the Client's/ Broker's custodian. Separate settlement records created on receiving confirmation from custodian. The first settlement record is for the bank to settle with the client and the second settlement record is for the bank to settle with the external broker. | G63: Yes
D64: Execute and Complete Parent Child Orders | E64: This processes explains execution of Parent Orders which in turn executes underlying child orders. This process also explains - Amendment to Parent transactions and ensure that the amendment is automatically updated in all Child transactions - Bulk authorisation of Child transactions when Parent transaction is authorised - Deletion/ replacement of Parent Child transactions | G64: Yes
D65: Execute IPO Order | E65: This process describes the steps involved in executing IPO order. The Dealer executes the order by furnishing broker details like Nominal Allotted and Price. Nominal Allotted can be a full, partial or null. Once executed, the execution details are updated and trade is created for further processing. Refund in case of null or partial allotment of nominal is also processed at the time of execution. | G65: Yes
D66: Execute Security Order (Manual) | E66: The Trade execution desk will place the order in the market (manually or electronically), after the order is captured by an Investment Representative and placed on a dealer blotter. Once executed, the execution details are updated either manually or electronically via an incoming SWIFT message. | G66: Yes
D67: Execute Fund Order (Manual) | E67: The execution desk will place the order in the Fund house after the order is captured by an Investment Representative and placed on a fund blotter. The execution details are updated and the security trade is created. | G67: Yes
D68: Initiate Cancellation of Funds Subscription | E68: This process describes the steps involved in Cancellation of Subscription. Investors have the right to cancel their subscription to a fund within a certain number of days from the date of purchase of units (cancellation/ cooling period). Cooling period is defined in Security Master. On triggering the cancellation of subscription, Transact creates a relative Fund Redemption order for the same Customer, Nominal as defined in subscription trade. Charges for this cancellation can also be levied on the customer when the same is defined in the Multiple Charges setup. | G68: Yes
D69: Initiate Fund Order | E69: The process describes the steps involved in Capturing Mutual Fund Order (Subscription or Redemption). Order is initiated by the customer and account balance is checked and blocked before booking is done. While capturing fund order details, Invest option type can be set either as cash or reinvestment for Dividend type Funds. Reinvestment type at order level is possible only if the Fund allows reinvestment (i.e. Reinvestment option is set at the Security Master level). Depository for the order gets defaulted from security master based on Invest option type. For Funds where Net Asset Value is yet to be received from the Fund House, a dummy security is created and attached as upfront security in the security master. This upfront security gets defaulted to the order and execution of the order is based on this dummy security. Upfront Security trades are created assuming the Net Asset Value as 1. On receipt of actual Net Asset Value from the Fund House, the security position from upfront security is transferred to the actual security. | G69: Yes
D70: Initiate IPO Order | E70: This process describes the steps involved in capturing IPO order details. Once the order details are captured in Transact, the same is available for execution. IPO orders are for securities that are listed for IPO processing. Security Master application holds the details of Subscription Period, Lot Size, Minimum Offer Price, Maximum Offer Price, Type of Issue (Single Bid or Book building), Allotment Date, Listing Date and Refund date of IPO Security; these details are validated during Order Capture. | G70: Yes
D71: Initiate Parent Child Orders | E71: Bulk Orders with Multiple Customers can be separated into Customer Side and Market side such that any amendment or cancellation of one side does not impact the other. Security Orders can be created as Parent Child Orders where Parent Order will hold the Broker (Market) side and the Child Orders will hold each Customer's side. The Parent Child Orders are linked by a common Reference. The Parent child separation continues into Execution and Trade creation. The separation of an Order into Broker side and Customer sides can also be done at the time of execution. In this case, system would create separate trades – a Parent trade for the Broker side and child trades for each of the Customers. This functionality will make it possible for users to amend/cancel one or more Client legs of an Order/ Trade without impacting the Market side and vice-versa. | G71: Yes
D72: Initiate Security Order (1 Step) | E72: Order Details can be captured in Transact and order can be directly placed in the market. Since the order is directly placed without going through the Trade Execution Desk, all details will need to be captured and all system checks (e.g. validations) will be performed. If necessary, Manager approval will be provided. | G72: Yes
... D78: Receive Instructions For Securities Transaction | E78: The request for trading is received from the customer. Customer and Portfolio Information will be checked in Transact before Initiating the Trade. | G78: Yes
D79: 5.2.1.1.5 STP Equities
D80: Amend or Cancel Order (STP) | E80: The process describes the activities of Order Amendment/ Cancellation before the execution message (inward message) is received. | G80: Yes
D81: Complete and Authorise Trade (STP) | E81: Based on the broker confirmation the trade will be authorised automatically in Transact via an incoming SWIFT message and system generates Customer confirmation, broker advice and custodian messages. Based on Broker conditions set, aggregated messages will be received which will get matched with Aggregation and Reconciliation records generated by the system. Once Reconciliation is matched, underlying trades will be automatically authorised. This will trigger aggregated settlement instructions which will match and settle individual settlement records. | G81: Yes
D82: Execute Security Order (STP) | E82: After an order has been initiated, a SWIFT Message is sent to the counterparty. After the execution, a SWIFT message will be received. The trades are updated in Transact based on the SWIFT messages (e.g. fully or partially executed). If Order Routing exists for the respective Order, based on parameter set up the system creates a trade either in broker dealer/ default branch company and a mirror trade created in the Origination Company or vice versa. | G82: Yes
D83: Initiate Direct Trade (Securities) | E83: Direct trades could be own book investments/ investments done for institutional clients/ investments done for the managed portfolio. This process describes the capture of a confirmed direct trade in the system. | G83: Yes
D84: Initiate Security Order (STP) | E84: Order Details are captured in Transact. If necessary, Manager approval will be provided. System checks (e.g. validations) will be performed and an MT502 SWIFT message will be automatically sent. | G84: Yes
D85: Perform Pre Matching (STP) | E85: After trade authorisation is completed, pre matching is performed by the system and the items parked in repair queue are either amended or taken up with counter party for correction. | G85: Yes
D86: Process SWIFT MX Messages | E86: SWIFT has introduced a new message type expressed in XML syntax, which is more flexible and easier to implement than the previous generation of message types (MT). These message types are developed in accordance with ISO 20022 standard and are referred to as MX messages. Transact supports MT502, MT509 and MT515 MX messages. | G86: Yes
D87: Process Cancellation of Trade Confirmation (MX Message) | E87: This process describes the activities involved in processing an incoming cancellation of trade confirmation (setr.029). The setr.029 message is sent by an executing party to an instructing party to cancel the referenced Securities Trade Confirmation message that was previously sent. The system updates the Trade Message Details with the incoming setr.029 details along with the link reference of setr.027 message. The back office user can review the details and take necessary action accordingly. | G87: Yes
D88: Process Confirmation of Trade (MX Message) | E88: This process describes the activities involved in processing an incoming Trade confirmation (setr.027) message sent by an executing party to an instructing party. The system updates the Trade Message Details and matches the Trade with the incoming message using the parameters such as Nominals, Amount, Price, Trade Date and Value Date. When matched, the system automatically authorizes the trade, otherwise the trade will remain in unauthorized status and the unmatched reason is updated for the back officer user review. When the trade is authorized, based on the setup, related setr.030 message is sent to the counterparty. | G88: Yes
D89: Route Security Orders | E89: This process describes the activities involved in in routing orders based on regulatory requirements like US – Regulation R. In a multi book set up, Order received in a branch company is routed to another branch company for execution and subsequently trade gets created based on parameter set up at company or system level. | G89: Yes
D90: 5.2.1.2 Settlement
D91: Complete Parent Child Aggregation | E91: Aggregation can be set for Parent/Child trades. In the case of Parent Child Trades, for Parent Trades Broker side will be aggregated. Aggregated MT515 message will be received, matched and reconciled and aggregated Settlement message (MT54X) will be sent to the Depository. During the process system would authorise the underlying trades before sending aggregated settlement message. The MT54X message will be suppressed in the Parent Trade. All Parent Trades with same Depository will be aggregated and single MT54X will be sent to the Parent Depository from SP.RECONCILIATION record. All Child Trades with same CU. DEPOSITORY will be aggregated and separate MT54X will be sent to the Cu.Depository (Sub-account). It is also possible to aggregate the Nostro posting and send a consolidated MT518. If this is required for a Broker, then the field NOSTRO.AGGREGATION in CUSTOMER.SECURITY has to be set. In the parameter SC.STD.SEC.TRADE, a synthetic portfolio should be set in the field AGGR.SYN.PORT and a Suspense account category should be set in AGGR.SUSP.CAT. In this case, once a Trade is created for a Broker with Nostro Aggregation set, system would default the Synthetic account on the Broker side instead of the Nostro. Simultaneously, system would create another Aggregated Trade on IHLD. The Aggregated trade will have the Synthetic Portfolio and Synthetic Account on the Customer Side and the Street Side Broker and Nostro account on the Broker side. Every time a new Trade is created for the Broker, system would update the total Nominals and Average Price in the Aggregated Trade. At the Cut-off time, a service would authorise the Aggregated trade and trigger a consolidated MT518 from that trade. Consolidated Nostro entry would also be posted. If the Underlying Broker trades are not authorised at this stage, system would automatically authorise them. If aggregation is based on Broker and Stock Exchange, then the cut-off time will be taken from the Stock Exchange. If aggregation is set only at Broker level, cut off time will be the time set in field MT515.CUT.OFF.TIME in CUSTOMER.SECURITY. If Settlement aggregation is set, then the MT54X settlement message will be sent on authorisation of the Aggregated Trade. The Settlement message will be sent from the SP.RECONCILIATION record as explained in Note1 above. The aggregated Trade can also be manually authorised by the User. | G91: Yes
D92: Correct Trade Errors | E92: The process describes the activities to be taken to correct a wrong Trade. This could either be a cancellation/ reversal of the Trade or just amending certain fields before settlement. | G92: Yes
D93: Execute Settlement (Securities) | E93: This process deals with the settlement of deals. On the settlement date, the deal could be settled either on a contractual basis or actual. Contractual deals are effectively “no fail” trades and when a contract is completed, it is assumed that settlement has taken place. In case of actual deals, positions are updated on completing the transaction as "unsettled" and accounting is raised to suspense, till the settlement of security/cash is done. All accounting and position entries will be automatically updated by Transact. For all aggregated settlement instructions received, the incoming settlement status messages and the settlement confirmation messages will also be aggregated. If there is a match against a reconciled record, the status as in the incoming message will be updated for all the underlying individual trades. On receipt of settlement confirmations, in case of a match, the underlying individual trades will be identified and settled. Settlement will be full or partial based on the match. | G93: Yes
D94: Perform Allegement Management | E94: This process describes the activities involved in processing of Incoming MT578 message from the Custodian. The details of MT578 are recorded with status "RECEIVED" or "ERROR" based on the receipt of mandatory fields. The Allegement Details can further be "Accepted/ Rejected" by the Account Owner so as to send the relevant Swift message to the custodian. | G94: Yes
D95: Process Bilateral Split of Settlement Instructions | E95: This process describes the activities involved in Bilateral splitting of the settlement instructions. Bilateral splitting takes place when both parties instruct for a split to take place. In a bilateral splitting, once the party (bank) and the counterparty enter into an arrangement the original settlement instruction sent to the custodian gets cancelled and further split takes place based on the quantity available for settlement with the party/ counterparty. Splitting of settlement instructions is initiated in three ways; 1. Splitting original settlement instructions 2. Split on split 3. Splitting after netting. The outstanding trade settlements get reviewed by the settlement analyst who decides on initiating the splitting instructions by creating an entry in SP.SPLIT.SETTLEMENT. Upon authorization, relevant settlement messages are sent out for each split with the split reference as the transaction reference. | G95: Yes
D96: Perform Trade Aggregation and Settlement | E96: Trades can be aggregated for Brokers who have been set for Aggregation. System supports Aggregation of Trades to receive an aggregated MT515 message and to send aggregated Settlement message (MT54X or sese.023) to the Depository. The aggregated MT515 will be reconciled with the underlying aggregated trades and if it is matched, system would authorise the Trades and send out an aggregated settlement message. It also possible to aggregate the Nostro posting and send a consolidated MT518. If this is required for a Broker, then the field NOSTRO.AGGREGATION in CUSTOMER.SECURITY has to be set. If aggregation is required by Stock Exchange, then the field STK.EXC.AGGREGATE in CUSTOMER.SECURITY record of the Broker should be set. If STK.EXC.AGGREGATE is set, then trades will get aggregated only if both Broker and Stock exchange conditions are met. Field AGGREGATION should be set for those Stock exchanges for which aggregation is required. The Cut Off time for aggregation is to be set in the STOCK.EXCHANGE record in this case. At the Cut-off time, a service would authorise the aggregated trade and trigger a consolidated MT518 from that trade. Consolidated Nostro entry would also be posted. If the Underlying Broker trades are not authorised at this stage, system would automatically authorise them. (If aggregation is based on Broker and Stock Exchange, then the cut-off time will be taken from the Stock Exchange. If aggregation is set only at Broker level, cut off time will be the time set in field MT515.CUT.OFF.TIME in CUSTOMER.SECURITY) | G96: Yes
D97: Hold and Release Settlement Instruction (CSDR) | E97: This process describes the activities involved in "Hold and Release" of settlement instruction. As per Central Securities Depository Regulation (CSDR), instruction 'on hold' will undergo matching process but is not eligible for settlement until both parties have released their respective settlement instructions. Hold and release of settlement instruction is managed via SC.INST.HOLD.REL application. Hold and release settlement instruction can be sent from instructing party to executing party via MT530 or MT540-43, based on configuration done in the Securities Parameter file. The transaction is ready for settlement when both parties release settlement instruction. Hold and release of settlement instruction could happen multiple times during the settlement life cycle. | G97: Yes
D98: Process Trade Netting | E98: This process describes the activity involved in the netting of trade settlement instructions. Trade Netting takes place when both the buy and the sell, on the broker side, are dependent on one another, and the broker is insufficient in both legs. The bank and the broker reduce settlement risk and any subsequent penalties, by allowing trades to net against one another reducing the unsettled position. Trade netting is done via the application SP.NET.SETTLEMENT. Trades get matched by comparing attributes like Security, Broker, Depository, Trade Currency, Stock Exchange, and Delivery Instruction to arrive at the final net nominal and net transaction code. Based on the net nominal, Net Trans Code gets updated and a corresponding reconciliation record is created. Settlement instructions for the netted trades are cancelled and a new instruction is sent from SP.RECONCILIATION with the Net Nominal and Net Trans Code. Re-netting is allowed by amending the existing SP.NET.SETTLEMENT record with the addition of a New Transaction Reference involved in netting. Any netted transaction can be split again using Split Settlement. | G98: Yes
D99: Manage Penalty Processing for Failed Settlements (CSDR) | E99: This process details on the calculation and posting of cash penalties for failed settlements. Calculation of penalty fees is based on Penalty rates configured in the application SC.SETT.PENALTY.RATES. Late Matching Fail Penalty (LMFP) and Settlement Fail Penalty (SEFP) are processed based on the Intended Settlement Date of the transaction being settled. Daily penalty can be received either via MT537 or MT548 based on CSDR parameter setup. System receives and processes the daily penalty details for each transaction until the settlement is completed. On receipt of net monthly penalty details for each counterparty, system updates the details received via an incoming MT537 message. The details are available for the settlement analyst to review and post the penalty fee calculated. | G99: Yes
D100: Process Bilateral Cancellation of Settlement Instruction (CSDR) | E100: This process describes the activities involved in processing bilateral cancellation of settlement instruction. As per Central Securities Depository Regulation (CSDR), matched instructions cannot be settled unilaterally. Matched instructions can only be cancelled if both counterparties request for cancellation of their instructions. Until the cancellation confirmation is received from the market, the instruction will remain eligible for settlement. Depositories for which bilateral cancellation is applicable must be defined in CSDR parameter file. Request for cancellation can be initiated either by bank or by counterparty. System updates the status of cancellation received via MT548 message from custodian and reverses the trade when both parties agrees for cancellation of instruction. | G100: Yes
D101: 5.2.1.3 Reconciliation
D102: Perform Stock Reconciliation | E102: Periodically, holding with various custodians will need to be reconciled with statements sent by such custodians. This Process outlines the activities to be performed for such Stock reconciliation. It also includes processes for matching unmatched items. | G102: Yes
D103: Reconcile Nostro Accounts | E103: Periodically, Nostro accounts as in Bank's books will need to be reconciled with the account statement sent by the Nostro Bank. The statements may be received via SWIFT or physically and Transact automatically matches items and any unmatched items will need to be investigated. | G103: Yes
D104: 5.2.1.4 Miscellaneous
D105: Add or Check-in To Vault | E105: This process is used to enter the documents of title, certificates or any other miscellaneous valuable items deposited by the Bank's Customer. Any entry made through this option will not be included in the Portfolio Valuation of the Customer. Collateral items, which may be stored in the Vault, can be controlled and monitored through this application. | G105: Yes
D106: Capture MiFID Details for Customer Profiling | E106: This process describes the activities involved in calculation of Investment Program score based on Customer response. Customers are profiled based on the parameter setup and assigned suitable Investment Program. The back office user can further modify the total points scored by the customer and assign Investment Program based on revised points. This Investment Program will be assigned whenever a new Portfolio is created for the customer. | G106: Yes
D107: Create Credit Facility | E107: This process describes the activities involved in the creation of a Credit Facility for a customer based on his Security Holdings. Based on the Facility Product chosen, response to respective questionnaires are captured and related documents need to be submitted for further evaluations. The application is then evaluated with respect to the creditworthiness of the customer and sanctioned by updating the sanctioned amount. The limit will be created for the amount sanctioned and collateral will be created based on the assets pledged. Customer can avail or utilize this limit through a Margin Loan. | G107: Yes
...

Sheet (6) Online Channels
D2: Business Area | E2: Online Channels Processes | G2: In Scope
D3: Total no. of processes | E3: =COUNTIF(E8:E133,"*") -> 116 | G3: =COUNTIF(G8:G133,"Yes") -> 116
D4: Release | E4: ='(5) Private Wealth Management'!E4 -> R25 Model Bank
G6: Scoping
B7: Process Area | C7: Scenario | D7: Process | E7: Process Description | G7: In Scope
B8: Online Channels Processes
C9: 6.1 User Management - Online Channels Processes | G9: =COUNTIF(G11:G26,"Yes") -> 13
D10: 6.1.1 Initiation
D11: Receive Request For Online Channels | E11: This process describes activities associated with receipt of an Online Channels request from an existing Retail/ Corporate or an Intermediary customer. Validations are carried out on the request and appropriate customer category identified, before creation of the user id in the system. | G11: Yes
D12: 6.1.2 User Setup
D13: Create Intermediary Internet Banking User | E13: This process describes activities associated with the creation of an intermediary internet banking user id. As part of this process, for each customer whose portfolio falls under the jurisdiction of the intermediary, a proxy services arrangement is created, in which the permissions to portfolio(s) are defined. This is followed by creation of a new internet services arrangement ID where the user rights and arrangement preferences are specified. Finally, the Customer numbers are linked to the arrangement ID to generate the Intermediary user ID. | G13: Yes
D14: Create Online Channels Corporate User | E14: This process describes activities associated with the creation of a corporate online channels user id. As part of this process, a new Online services arrangement ID is created first where details of Customer, Permissions (account and contract level ), Product Access and Daily Protection Limit are defined. Finally an external user ID is created by linking the Customer number to the arrangement ID. At this stage specific menu options are enabled depending on the role created. | G14: Yes
D15: Create Online Channels Retail User | E15: This process describes activities associated with the creation of a retail online channels user id. As part of this process, a new arrangement ID is created first, where details of accounts and products the Retail user will have access to is defined. This is followed by creation of channel permission. Finally, external user ID is created by linking the Customer number to the arrangement ID. | G15: Yes
D16: Create Private Advisory Internet Banking User | E16: Intermediary private banking clients can be classified as advisory and discretionary internet banking users. This process describes the set up of private advisory users. A favourites list can be created for advisory users. | G16: Yes
D17: Create Private Discretionary Internet Banking User | E17: Intermediary Internet banking user clients can be classified as Discretionary and Advisory internet banking users. This process describes the set up of private discretionary users. | G17: Yes
D18: Set Up Mandates and Signatory Groups * | E18: The process depicts the set up of signatory groups and mandates. Customer is attached to respective signatory group. Mandate Application group is formed by logically grouping Transact applications/ versions. The mandate requirement can be defined for customer, account or portfolio and in turn linked to the appropriate application group and mandates. | G18: Yes
D19: 6.1.3 Administration
D20: Manage Messages (Online Channels Admin) | E20: This process deals with managing the messages of Customer Service Agent. This includes messages received from Customer, replying to the message & composing a new message to Online Channels Customer. | G20: Yes
D21: Manage User Amendments (Online Channels Corporate) | E21: This process deals with amendments to Arrangement/ External user. The user rights, daily limits, UI Appearance, access to various products, password review frequency etc. can be amended. | G21: Yes
D22: Manage User Amendments (Online Channels Retail) | E22: This process deals with amendments to Arrangement/ External user. The user rights, daily limits, UI Appearance, access to various products, password review frequency etc. can be amended. | G22: Yes
D23: Manage User Amendments (PWM Internet Banking) | E23: This process deals with amendments to Arrangement/ External user. The user rights, daily limits, UI Appearance, access to various products, password review frequency etc. can be amended. | G23: Yes
D24: 6.1.4 Self Registration and User Profile
D25: Initiate Self Registration (Online Channels) | E25: This process deals with the initiation of request for the new Online Channels access by an existing customer, through self registration. | G25: Yes
D26: Perform Amendments To User Profile (Online Channels Retail) | E26: This process describes the activities associated with amending online channels retail user profile. The user is allowed to update his nick name and contacts through online banking channels. | G26: Yes
C27: 6.2 Online Channels Retail Processes | G27: =COUNTIF(G28:G46,"Yes") -> 19
D28: Amend or Delete Travel Notifications (Online Channels Retail) | E28: This process describes the steps involved in amending or deleting an existing travel notification by customer through online channels. | G28: Yes
D29: Cancel Direct Debit (Online Channels Retail) | E29: This process describes the activities associated with the cancellation of a Direct Debit mandate through online channels (Inward/Outward). | G29: Yes
D30: Create New Account (Online Channels Retail) | E30: This process describes the steps involved in initiating a new account creation request by the user through online banking channels. | G30: Yes
D31: Create Term Deposit (Online Channels Retail) | E31: This process describes User initiation of a new term deposit request through online channels. Funding of the deposit can be done during deposit creation or before a fixed number of days defined in cancel period, failing which system will automatically cancel the deposit. | G31: Yes
D32: Capture Travel Notifications (Online Channels Retail) | E32: This process describes the steps involved in capturing travel notifications by the customer through online banking channels. Travel details like place and period of travel, purpose of travel can be submitted by the customer through online channels. Travel notifications are marked as expired and moved to history automatically on reaching the travel end date. | G32: Yes
D33: Initiate Cheque Book Request (STP) (Online Channels Retail) | E33: This process describes the steps involved in straight through processing for a cheque book request, initiated from Online Channels. On receiving the request Transact checks if stock entry is available for the account. Cheque book will be issued instantly, if request is from an account for which Stock Entry with balance is available in Stock Register. If the cheque book request is from an account for which stock entry is not available, Transact creates the stock entries, updates the register and then issues the cheque book. | G33: Yes
D34: Initiate Payment Order (Online Channels Retail) | E34: This process describes Payment Order creation through Online channels by an Online Channel Personal Banking user. Payment order refers to a directive to a bank from a bank account holder instructing the bank to make a payment or series of payments to another bank account. | G34: Yes
D35: Initiate Quick Pay (Online Channels Retail) | E35: This process describes the feature of Immediate Payment in Payment Order. This will allow user to choose payment method if the beneficiary has more than one payment method and user can choose different currency from the default one. | G35: Yes
D36: Initiate Stop Payment of Cheque (Online Channels Retail) | E36: This process describes steps involved in initiating a request for stop payment of cheque through Online Channels. | G36: Yes
D37: Login to Online Channels Retail | E37: This process describes the steps involved in a Branch User/Manager logging into TCUA and performing activities (Create/ Manage/ Authorise Customer Profile, Direct User, Indirect User, Role) as an User Administrator. | G37: Yes
D38: Manage Alerts (Online Channels Retail) | E38: This process describes the steps involved in subscribing/ unsubscribing an alert through Online Channels. | G38: Yes
D39: Manage Consent (Online Channels Retail) | E39: This process describes the steps involved in capturing, through online channels, Customer's consent for using his personal data. The purpose of using one's personal data for specific tasks/ types (e.g.: direct marketing, data profiling, loan credit check, etc.) is displayed and the user can manage his personal data consent by giving/ removing the consent for a specific purpose. Only the consent types that are not expired will be displayed and those that are temporarily blocked by bank can only be viewed. | G39: Yes
... D46: View Accounts or Transaction Details (Online Channels Retail) | E46: This process describes the activities to view accounts, account details, recent transactions and to print/ download the transaction details. | G46: Yes
C47: 6.3 Online Channels Corporate Processes | G47: =COUNTIF(G48:G85,"Yes") -> 38
D48: Accept or Reject Export LC Amendments (Online Channels Corporate) | E48: This process describes the activities of accepting or rejecting the amendments of an Export LC by a Online Channels Corporate User. | G48: Yes
D49: Capture Documents and Conditions - LC (Online Channels Corporate) | E49: This process describes the activities for setting up standard documents and conditions, which can be used within the LC and MD application. | G49: Yes
D50: Execute Direct Debit (Online Channels Corporate) | E50: This process details the various types of debit payments to be effected through upload from Online Channels viz., internal account debit or sending out a direct debit claim file to an external bank. | G50: Yes
D51: Initiate Cheque Book Request (Online Channels Corporate) | E51: This process deals with the initiation of new cheque book request through Online Channels by any existing user. | G51: Yes
D52: Initiate Guarantee Amendments (Online Channels Corporate) | E52: The Process describes the activities of Amending a Guarantee (Issued) by a Online Channels Corporate User. | G52: Yes
D53: Initiate Guarantee Issuance Request (Online Channels Corporate) | E53: This process describes the activities of Initiating a Guarantee Issuance Request by a Online Channels Corporate User. | G53: Yes
D54: Initiate Import LC Issue (Online Channels Corporate) | E54: This process covers the initiation of an Import LC by the Customer through Online Channels. The system automatically checks for availability of limits and upon successful verification, routes the transaction to a bank user's queue for further processing. | G54: Yes
D55: Initiate Outward Collections (Online Channels Corporate) | E55: This process describes the activities of initiating an Outward (Export) Collection by a user through Online Channels. | G55: Yes
D56: Initiate Payment Order (Online Channels Corporate) | E56: This process describes initiation of transfer of funds through Online Channels by a Corporate Online Channels user. | G56: Yes
D57: Initiate Stop Payment Of Cheque (Online Channels Corporate) | E57: This process describes steps involved in initiating a request for stop payment of cheque through Online Channels by an existing Corporate user. | G57: Yes
D58: Lodge Claim Under Guarantee (Online Channels Corporate) | E58: This process describes the activities of Invocation claim and settlement available for Guarantees Received (CL type of guarantees in the system) by an Online Channels user. | G58: Yes
D59: Login to Online Channels Corporate | E59: This process describes the activities for a Online Channels Corporate User/ Supervisor to log in as well as to select the transactions to be performed. | G59: Yes
... D85: View Guarantees Received (Online Channels Corporate) | E85: This process describes the activities of viewing the Guarantees Received by a Online Channels Corporate User. | G85: Yes
C86: 6.4 Private Wealth Management Internet Banking Processes | G86: =COUNTIF(G87:G122,"Yes") -> 36
D87: Amend or Cancel Order (PWM Internet Banking) | E87: Orders initiated through internet banking can be modified in this process. Derivatives, Mutual funds and securities order can be modified or cancelled. | G87: Yes
D88: Cancel Future Dated Payments (PWM Internet Banking) | E88: This process helps the Customer view a list of payments scheduled for a future date and cancel them through internet banking. | G88: Yes
D89: Delete Beneficiary (PWM Internet Banking) | E89: This process describes activities associated with deleting a beneficiary through internet banking. This can be an internal customer of the bank or an external beneficiary. | G89: Yes
D90: Enquire on Accounts (PWM Internet Banking) | E90: Process describes the activities related to account enquiries (incl. statements) | G90: Yes
D91: Execute Funds Transfer (Online Channels) | E91: This process deals with the execution of funds transfer requests originated through Online Channels. | G91: Yes
D92: Initiate Derivatives Order (PWM Internet Banking) | E92: This process indicates the activities involved in initiating a derivatives (futures & options) order through internet banking. | G92: Yes
D93: Initiate Mutual Funds Order (PWM Internet Banking) | E93: The process is initiated by a customer/ intermediary through internet banking for placing a MF order, the account balance is checked and blocked before the booking is performed. | G93: Yes
D94: Initiate New Payment or Transfer (PWM Internet Banking) | E94: This process describes initiation of funds transfer through internet banking by a PWM internet banking user. | G94: Yes
D95: Initiate Portfolio Analysis (PWM Internet Banking) | E95: This process describes the different options for portfolio analysis, using pre-defined categories. | G95: Yes
D96: Initiate Research Reports (PWM Internet Banking) | E96: This process helps in analysing current market trend by checking the economy reports and market stability. | G96: Yes
D97: Initiate Securities Order (PWM Internet Banking) | E97: This process describes the activities for Order placement. Order details can be captured in Transact - Internet Banking and will be placed for execution. | G97: Yes
D98: Login to Private Wealth Internet Banking - Advisory | E98: This process describes the activities for a Private Wealth Internet Banking User to log in as well as to select the transactions to be performed. | G98: Yes
... D122: View or Download Portfolio Statements (PWM Internet Banking) | E122: Process to view/ download Portfolio statements. | G122: Yes
C123: 6.5 Online Channels User Administration Processes (TCUA) | G123: =COUNTIF(G124:G133,"Yes") -> 10
D124: Authorise or Reject External Users for Online Channels | E124: This process describes the steps involved in authorising Direct/ Indirect Users. Direct Users are External users created for a customer profile (Online service arrangement) and can be authorised by the Bank. Indirect Users are External users created either for a customer profile (Online service arrangement) or User Role (sub arrangement of the Online service arrangement) and can be authorised by the Bank and by a Corporate User. | G124: Yes
D125: Authorise or Reject Online Channels Customer Profile | E125: This process describes the steps involved in authorising Customer Profile. Customer Profile is an online service arrangement created to set online access for a user. Permissions and privileges are set for an user in the online service arrangement. | G125: Yes
D126: Authorise or Reject Online Channels Customer Role | E126: This process describes the steps involved in authorising Online Channels Customer Role. Permissions, Privileges, Limits amended in Role (Online Services sub-arrangement) can be finalised by authorising the sub arrangement. | G126: Yes
D127: Create Direct or Indirect User for Online Channels | E127: This process describes the steps involved in creating Direct/ Indirect online channel users. Direct User is a customer of the bank and is the owner of the customer profile (Online service arrangement) for which the external user is created. Direct Users can be created only by the Bank. Indirect User is not a customer of the bank but is granted access to perform miscellaneous activities. Indirect user can be created by the Bank or by a Corporate User having Administration privileges for an User Role (sub arrangement) or a Customer Profile (master arrangement). | G127: Yes
D128: Create Online Channels Customer Profile | E128: This process describes the steps involved in creating a Customer Profile for online access. This is achieved through the creation of an Online service arrangement. This online service arrangement defines the customer type (Retail/ Corporate), permissions and privileges assigned to the user for access. The following properties are set in the master arrangement while creating online profile: (a) Licensing - This property restricts the maximum no. of users and roles to which this online profile can be assigned to. (b) Permission - Account specific permission to see/transact/exclude. (c) Privilege - Functions that the user would be allowed to perform in Online Banking e.g. Perform Bulk Payment, Enable Trade Finance functionalities etc. (d) Availability - Specify day/time for the user to perform activities. (e) Daily Limit - Daily transaction limit for the user. | G128: Yes
D129: Create Role for Online Channels User | E129: This process describes the steps involved in creating a role for an online user to define the boundary of his/her actions. Role can be created by the Bank or by a Corporate User having Administration privileges. The Role provides the possibility to give restricted and targeted access to groups of users. A Role can only restrict access that the Master Arrangement (Customer Profile) defines, not grant additional access. Indirect user can be created for an User Role (sub arrangement) or a Customer Profile(master arrangement). The following properties are set in the sub-arrangement while creating the role for online user: (a) Permission - Account specific permission to see/transact/exclude (b) Privilege - Functions that the user would be allowed to perform in Online Banking e.g. Perform Bulk Payment, Enable Trade Finance functionalities etc. (c) Availability - Specify day/time for the user to perform activities. (d) Daily Limit - Daily transaction limit for the user. | G129: Yes
D130: Login to Online Channels User Administration | E130: This process describes the steps involved in performing activities like Creating, Managing, and Authorising Customer Profile, Direct User, Indirect User, Role by a Bank User after logging into TCUA as an User Administrator. | G130: Yes
D131: Manage Online Channels Customer Profile | E131: This process describes the steps involved in viewing or amending Online Channels Customer Profile (Online Service Arrangement). Details of the customer profile selected can be viewed and a Direct User/ Indirect User/ Role created for the selected profile by the Online Channels User. Access to Online Channels can be amended by amending the arrangement. | G131: Yes
D132: Manage Online Channels Customer Role | E132: This process describes the steps involved in viewing or amending Online Channel Role. Permissions, Privileges, Limits set for online access can be modified by amending the Role (Online Services sub-arrangement). | G132: Yes
D133: Manage Online Channels User | E133: This process describes the steps involved in viewing or amending online channel user details. Direct User details can be amended by the Bank while Indirect Users details can be amended by both Bank and Corporate User. | G133: Yes

Sheet (7) Security Management (SMS)
D2: Business Area | E2: Security Management Processes | G2: In Scope
D3: Total no. of processes | E3: =COUNTIF(E8:E15,"*") -> 5 | G3: =COUNTIF(G8:G15,"Yes") -> 5
D4: Release | E4: ='(6) Online Channels'!E4 -> R25 Model Bank
G6: Scoping
B7: Process Area | C7: Scenario | D7: Process | E7: Process Description | G7: In Scope
B8: SMS Processes
C9: 7.1 SMS Set Up | G9: =COUNTIF(G10:G11,"Yes") -> 2
D10: Set Up Override | E10: This process deals with creating overrides for various transactions and definition of user hierarchy for approving the overrides. | G10: Yes
D11: Set Up Password | E11: This process describes activities associated with the initial specification of password characteristics by the bank viz., minimum length, number of numeric, other characters etc. | G11: Yes
C12: 7.2 User Set Up and Maintenance | G12: =COUNTIF(G13:G15,"Yes") -> 3
D13: Reset Password | E13: This process describes activities associated with resetting the password. A new password is created in the system and communicated to the user. As a security measure, the user will be forced to change it on the first sign-on. | G13: Yes
D14: Set Up User | E14: This process describes creation of a user record. As part of this activity, access rights/restrictions to specific applications and versions along with the user name are set up in the system. | G14: Yes
D15: Set Up User For Role Based Home Page | E15: This process describes creation of a user record and attachment of pre-configured 'role based home page' to the user. The user so assigned with role based home page will be having access to the defined set of menus as available to the particular role. | G15: Yes

Sheet (8) Financial Accounting
D2: Business Area | E2: Financial Accounting Parameter Maintenance Processes | G2: In Scope
D3: Total no. of processes | E3: =COUNTIF(E8:E48,"*") -> 34 | G3: =COUNTIF(G8:G48,"Yes") -> 34
D4: Release | E4: ='(20) Financial Risk (FRM) '!E4 -> R25 Model Bank
G6: Scoping
B7: Process Area | C7: Scenario | D7: Process | E7: Process Description | G7: In Scope
B8: Financial Accounting Parameter Maintenance Processes
C9: 8.1 Financial Accounting Parameters Maintenance | G9: =COUNTIF(G10:G15,"Yes") -> 6
D10: Input And Maintain Journal Entries | E10: Process is for creation/ amendment or reversal of journal entries (examples: purchase of assets, depreciation entries etc.) either through data capture or through funds transfer. | G10: Yes
D11: Maintain Accounting Static Data | E11: Process for maintaining the category codes, transaction codes, special transaction codes and internal accounts definition. | G11: Yes
D12: Maintain Bank Related Parameters | E12: This process depicts the activities involved in maintaining the Bank related parameters which include maintaining the Company parameters, language(s), countries, country group and holiday list. | G12: Yes
D13: Maintain Customer Related Parameters | E13: This process is for setting up/ maintaining the parameters related to Customer status, target, industry, sector, relationship manager (DAO codes) and Customer relationship codes. | G13: Yes
D14: Maintain Finance Related Parameters | E14: Process for maintaining the parameters relating to currency market, currency codes, department & DAO codes, basic interest rates, and periodic interest rates such as LIBOR etc. | G14: Yes
D15: Retrieve And Control Accounting Entries | E15: Process for viewing the report pertaining to accounting entries created online or at COB and taking corrective action if there are any differences in batch posting. | G15: Yes
C16: 8.2 Accounting Entries Parameter Maintenance | G16: =COUNTIF(G17:G24,"Yes") -> 8
D17: Define And Maintain Accounting Policy | E17: In this process the general rules for maintaining the accounting policies such as the value date/ trade date, accrual, currency position etc., are described. | G17: Yes
D18: Maintain Accounting Rules - AA | E18: This process is for setting up the accounting rules for AA related activities and events. | G18: Yes
D19: Maintain Accounting Rules - Account Based | E19: Process for maintaining parameters for account based applications like FT, Teller, DD etc. | G19: Yes
D20: Maintain Accounting Rules - Contract Based | E20: Process for maintaining parameters for contract based applications like LD, PD, SL and also for Bills and MD. | G20: Yes
D21: Maintain Accounting Rules - Contract Based (Securities) | E21: Process for maintaining parameters for securities based applications like MF, Corporate Actions, and Securities. | G21: Yes
D22: Maintain Accounting Rules - Contract Based (Treasury) | E22: Process for maintaining parameters for Treasury based applications like MM, FX, FRA, SWAP, REPO etc. | G22: Yes
D23: Review And Analyse Accounting Entries | E23: The process depicts the activities of an accountant who reviews and analyses the various types of accounting entries with a view to have a general control over the correctness of the entries passed by the user induced transactions. | G23: Yes
D24: Verify Accounting Journal | E24: Day end report of accounting transactions and summary journal is verified through this process. | G24: Yes
C25: 8.3 General Ledger Definition and Maintenance | G25: =COUNTIF(G26:G30,"Yes") -> 5
D26: Define And Maintain General Ledger Structure | E26: This process describes the GL structure to be adopted for Assets and Liabilities as well as Profit and Loss attributes of the bank. | G26: Yes
D27: Map Chart Of Accounts To GL Structure | E27: This process is for mapping the chart of accounts of a Bank to the Transact GL structure. | G27: Yes
D28: Open Internal Account | E28: This process depicts the activities associated with setting up of internal accounts of the Bank, which are in the nature of own-book accounts. | G28: Yes
D29: Review and Reconcile GL Line Balances With Contracts And Accounts | E29: This process is to review the GL report lines and drill down to the contract/ accounts balances and accounting entries, wherever necessary. | G29: Yes
D30: Review Central Reporting File | E30: The process is for the accountant to review the different type of balances of the assets and liabilities and P&L and, if necessary, to reconcile with the accounts and contract balances. | G30: Yes
C31: 8.4 Financial Reports - Definition and Maintenance | G31: =COUNTIF(G32:G36,"Yes") -> 5
D32: Define And Maintain GL Report Column And Range | E32: This process is for defining the GL report columns and range. | G32: Yes
D33: Define And Maintain GL Report Lines And Range | E33: This process is for defining or maintaining the GL lines and line ranges. | G33: Yes
D34: Define And Maintain GL Report Structure | E34: This process is for defining the header details and format of entries to be included in the GL or PL report. | G34: Yes
D35: Generate GL Reports Online | E35: This process is for generating a GL report on adhoc basis during the course of the day. | G35: Yes
D36: Set Up GL Reports For Batch Process | E36: This process is for identifying the GL reports to be processed and printed during the close of business batch job. | G36: Yes
C37: 8.5 Year End And Post Closing Events Processing | G37: =COUNTIF(G38:G42,"Yes") -> 5
D38: Define Post Closing Periods | E38: This process is for defining the End of Month post closing transaction codes and closing period. This process also describes the year end frequency dates to be parameterised. | G38: Yes
D39: Book Adjustment Entries | E39: This process is for inputting the adjustment entries affecting the Balance sheet and P&L items after the closing period for EOM or EOY is completed. The adjustment entries are made for the previous accounting period. | G39: Yes
D40: Maintain Year End Parameters | E40: This process describes some activities to be completed before the year end processing begins | G40: Yes
D41: Perform Financial Adjustments for Backdated Contract | E41: This process describes the activities involved in differentiating the accrual adjustment entries for the before period and the current period and the main changes required to identify adjustment entries for the current period and the period before now for backdated transactions. | G41: Yes
D42: Update General Ledger And Close Post Closing Period | E42: This process is for updating the general ledger on account of adjustment entries passed and closing the post closing period. | G42: Yes
C43: 8.6 Fixed Asset Management | G43: =COUNTIF(G44:G48,"Yes") -> 5
D44: Configure Fixed Asset Parameters | E44: This Process describes the parameterizations required for Fixed Asset Lifecycle Management. Fixed Asset Classification enables banks to group their fixed assets according to their characteristic's nature, purpose and depreciation requirements. Asset class is a high level grouping of fixed assets. Asset Type is a sub-classification of assets which are in-turn mapped to asset entities/ operational units. | G44: Yes
D45: Record and Manage Fixed Assets | E45: This Process describes the activities involved in the Fixed Asset Life-cycle Management. Fixed Asset life-cycle events (Register, Capital WIP, Purchase, Capital Improvement, Transfer, Depreciation, Dispose and Write-off) are recorded as a dated activity for efficient enquiring and tracking. Third Party vendors/ suppliers are captured through Beneficiary application. | G45: Yes
D46: Record and Manage Foreign Currency Assets | E46: This Process describes the activities involved in the Foreign Currency Asset Life-cycle Management. Foreign Currency Assets life-cycle events (Register, Purchase, Increase/ Decrease, Dispose, and Write-off) are recorded as a dated activity for efficient enquiring and tracking. Account Details of the foreign currency assets where the investment is made are captured through the Beneficiary application. | G46: Yes
D47: Manage Tangible Asset Arrangement | E47: The process describes the capturing of different transactional details related to the maintenance of asset catalog arrangement through arrangement activities. | G47: Yes
D48: Create Tangible Asset Arrangement | E48: This process describes the activities involved in creating an arrangement to capture the static details of an asset using tangible asset catalog. During arrangement creation, depending on the nature of asset like vehicles, equipments, and land-building, specific attributes are captured along with basic details of the asset. | G48: Yes

Sheet (9) Core Parameters
D2: Business Area | E2: Core Parameter Maintenance | G2: In Scope
D3: Total no. of processes | E3: =COUNTIF(E8:E24,"*") -> 9 | G3: =COUNTIF(G8:G24,"Yes") -> 9
D4: Release | E4: ='(8) Financial Accounting'!E4 -> R25 Model Bank
G6: Scoping
B7: Process Area | C7: Scenario | D7: Process | E7: Process Description | G7: In Scope
B8: Core Parameter Maintenance Processes
C9: 9.1 Define And Maintain Condition Priorities | G9: =COUNTIF(G10,"Yes") -> 1
D10: Set Up Condition Priorities For Applications | E10: This process is for setting up the condition priority records and application wise general conditions for grouping Customers and Accounts. | G10: Yes
C11: 9.2 Define And Maintain Tax Related Parameters | G11: =COUNTIF(G12,"Yes") -> 1
D12: Define And Maintain Parameters For Tax | E12: This process is for defining various types of taxes and associated rules for calculation of tax. | G12: Yes
C13: 9.3 Define Interest And Charges | G13: =COUNTIF(G14:G15,"Yes") -> 2
D14: Define Fees and Commissions Parameters | E14: This process is for defining the fees and commission parameters and setting up the amortisation rule. For Retail AA products Fees and Commission are defined through Product Conditions. | G14: Yes
D15: Set Up Parameters For Interest | E15: This process is for defining the basic interest and periodic interest parameters. | G15: Yes
C16: 9.4 Define Risk Profiling Parameters For Customer | G16: =COUNTIF(G17,"Yes") -> 1
D17: Set Up And Maintain Risk Profiling Parameters | E17: Basic parameters for setting up and maintaining the risk profiling of Customer is defined through this process. | G17: Yes
C18: 9.5 Image And Document Management Processes | G18: =COUNTIF(G19:G20,"Yes") -> 2
B19: ` | D19: Set Up Document Management Parameters | E19: This process handles the requirement for setting up of document management parameters by defining the class of document, status codes, grouping conditions and rules. | G19: Yes
D20: Set Up Image Management Parameters | E20: The process is for setting up the image management parameters such as the image type (example: photo, signature etc.) and define the path where they should be stored in the system. | G20: Yes
C21: 9.6 Online Company Creation Processes | G21: =COUNTIF(G22:G22,"Yes") -> 1
D22: Create Company Through an Online Service | E22: This process describes the activities involved in creating a company online (through a stateless connection like browser). When a new company is created in Transact, the process will create a new company record on hold with status set as NEW. Initiating service “Company Create” will create all relevant database tables and auto update key parameter tables. Record status is set as PROCESSING when the service is in progress and on successfully completion of Company creation, the status gets updated as ACTIVE. | G22: Yes
C23: 9.7 SWIFT Reference Directories | G23: =COUNTIF(G24:G24,"Yes") -> 1
D24: Receive and Execute SWIFT Reference Directory | E24: This process describes the steps involved in uploading of the SWIFTRef Identifiers All /SEPA Directory into Transact and the updates of the Temenos Central Bank Directory and optionally, based on the setup, and/or IBAN Plus Directories. | G24: Yes

Sheet (10) Islamic Banking
D2: Business Area | E2: Islamic Banking Processes | G2: In Scope
D3: Total no. of processes | E3: =COUNTIF(E8:E172,"*") -> 134 | G3: =COUNTIF(G9:G172,"Yes") -> 134
D4: Release | E4: ='(9) Core Parameters'!E4 -> R25 Model Bank
G6: Scoping
B7: Process Area | C7: Scenario | D7: Process | E7: Process Description | G7: In Scope
B8: Islamic Banking Processes
C9: 10.1 Islamic Customer | G9: =COUNTIF(G10:G11,"Yes") -> 2
D10: Create Customer (Islamic) * | E10: This process describes the activities involved in Customer creation, once the required background checks are completed, the user creates/ updates the customer record. AML and KYC checks are done and documents received from customer are scanned and attached to the customer record. | G10: Yes
D11: Manage Customer Engagements (Islamic) * | E11: This process begins with Front Office user checking on the customer's request and validating if the customer is already registered in the system. New customers will be recorded as prospects before continuing with AML and KYC check. Existing customer's records will be checked for cross-selling opportunities and verified if background checks or record updates are required. | G11: Yes
C12: 10.2 Islamic Account and Deposit | G12: =COUNTIF(G14:G23,"Yes") -> 9
D13: 10.2.1 Islamic Accounts
D14: Amend Mudaraba Account | E14: This process describes the receipt of an amendment request for an Mudaraba account from the Customer and capturing the amendments in the system. The amendment can also be bank initiated. Amendments related to account details/ holding pattern or to set dormancy/ posting restrict or to renegotiate arrangement/ adjust balances and bills of an Mudaraba account is done through new activity option in AA overview. | G14: Yes
D15: Open Mudaraba Account | E15: This process describes the steps involved in opening a Mudaraba savings account. Mudaraba savings account is a Profit-sharing partnership contract between a capital provider (Rab-ul-Mal) and a Mudareb (Fund Manager) in a Joint Investment. Client is the owner of the fund and Bank is just manager of the Fund. Mudaraba Savings accounts are mainly meant for Non-Trading customers who have some potential saving with a few number of transactions taking place. | G15: Yes
D16: Set or Reset Dormancy (AA) * | E16: This Process describes the activities associated with setting an arrangement as inactive/ dormant and resetting inactive/ dormant arrangement as active. In case there is no activity for a period specified in product condition, active accounts are automatically moved to inactive status. Dormancy status is automatically set for inactive arrangements with no activity (financial and non-financial) within the dormancy period set in product condition. Inactive/ dormant arrangements are automatically reset as active in case activity, defined as qualifying activities, is performed on the arrangement. Dormancy can also be set manually during inactive period and reset during dormancy period. | G16: Yes
D17: 10.2.2 Islamic Deposits
D18: Amend Mudaraba Deposit | E18: This process describes the receipt of an amendment request for a Mudaraba deposit from the Customer and updating the same on the system. | G18: Yes
D19: Amend Wakala Deposit | E19: This process describes the receipt of an amendment request for a Wakala deposit from the Customer and updating the same on the system | G19: Yes
D20: Open Mudaraba Deposit | E20: This process describes the steps involved in opening a Mudaraba deposit. Mudaraba is a contract between a capital provider(rab-ul-mal) and an entrepreneur(Mudarib) under which rabulmal provides capital to be managed by the Mudarib and any profit generated from the capital is shared between the rabulmal and the mudarib according to a mutually agreed profit sharing ratio. As mudaraba is a trust-based contract, the mudarib is not liable for losses except in case of breach of the requirements of trust or misconduct. Guarantees against negligence or misconduct could be taken from the mudarib as long as they are not excessively used by the capital provider. The contract should specify whether the mudaraba instrument is unrestricted or restricted (to specific location or type of investment as agreed between parties). It should also indicate the distribution ratio of profit between both parties (which cannot be a lump sum or a percentage of capital). The distribution ratio could be revised at future dates by agreement of both parties. | G20: Yes
D21: Open Wakala Deposit | E21: This process describes the steps involved in opening a Wakala deposit. Wakala is a Shari'a compliant contract in which the customer can authorize the Wakil (the Bank) to invest funds in Shari'a approved activities for profits. | G21: Yes
D22: Perform Early Withdrawal of Mudaraba Deposit | E22: This process describes steps associated with pre-closure of a Mudaraba deposit. | G22: Yes
D23: Perform Early Withdrawal of Wakala Deposit | E23: This process describes steps associated with pre-closure of a Wakala deposit. | G23: Yes
C24: 10.3 Islamic Profit Distribution System | G24: =COUNTIF(G25:G27,"Yes") -> 3
D25: Perform Profit Distribution | E25: This process describes the steps involved in distribution of profit using Profit distribution system (PDS). Profit distribution system is used to distribute the profit to Deposit/ Account holders by Islamic financial or shariah compliant institutions to comply with the religious prohibition on Interest on Loans. The intention is to promote "the concept of participation in a transaction backed by real assets, utilizing the funds at risk on a profit-and-loss-sharing basis". | G25: Yes
D26: Perform Reversal of Profit Distribution | E26: This process describes the steps involved in performing reversal of the last Profit Distributed by reversing the profit amount paid to customer accounts. | G26: Yes
D27: View Profit Distribution Projection - Simulation | E27: This process describes the steps involved in projecting profit distribution. Profit Distribution Projection - Simulation is used to simulate the profit distribution calculation details for a Future date by projecting the balances available till the last working date. The simulation results cannot be used for Profit distribution. | G27: Yes
C28: 10.4 Islamic Financing
C29: 10.4.1 Profit Upfront Sale | G29: =COUNTIF(G31:G50,"Yes") -> 18
D30: 10.4.1.1 Murabaha
D31: Create and Disburse Murabaha Finance (Manual) (IF) | E31: The process describes activities involved in maintaining manual disbursement in Murabaha Finance. | G31: Yes
D32: Create and Disburse Murabaha Finance (Scheduled) (IF) | E32: The process describes activities involved in maintaining Scheduled disbursement in Murabaha Finance. | G32: Yes
D33: Create Murabaha Contract (IF) | E33: The process begins with the receipt of a completed finance application from the Customer. The application could be received for named/ quantified Asset. The application is acknowledged at the front office and forwarded to the credit department for capturing collateral details and setting up limit. Asset details are captured and approved for purchase of Asset/ Commodity. | G33: Yes
D34: Initiate Murabaha Sale (IF) | E34: The process describes the process flow for initiating Murabaha sale. | G34: Yes
D35: Perform Murabaha Contract Status Change (IF) | E35: This process is used to purchase the approved asset from the Vendor. The contract workflow status is modified from "Approval" to "Purchase". | G35: Yes
D36: Receive Murabaha Finance Application (IF) | E36: The process deals with various activities associated with receipt of new financing request from a Customer and the processing of the application under Murabaha. | G36: Yes
D37: 10.4.1.2 Financial Ijara
D38: Create and Disburse Ijara Finance (Manual) (IF) | E38: The process describes activities involved in maintaining manual disbursement in Ijara Finance. | G38: Yes
D39: Create and Disburse Ijara Finance (Scheduled) (IF) | E39: The process describes activities involved in maintaining Scheduled disbursement in Ijara Finance. | G39: Yes
D40: Create Ijara Contract (IF) | E40: This process is applicable if the goods are ready and it has to be sold with the agreed fixed profit amount. The process begins with the receipt of a completed finance application from the Customer. Application could be received for named/ quantified Asset. It is acknowledged at the front office and forwarded to the credit department for capturing collateral details and setting up limit. Asset details are captured and approved for purchase of Asset/Commodity. | G40: Yes
D41: Initiate Ijara Sale (IF) | E41: The process describes the process flow for initiating Ijara sale. | G41: Yes
D42: Perform Ijara Contract Status Change (IF) | E42: This process is used to purchase the approved asset from the Vendor. The contract workflow status is modified from "Approval" to "Purchase". | G42: Yes
D43: Receive Ijara Finance Application (IF) | E43: The process deals with various activities associated with receipt of new financing request from a Customer and the processing of the application under Finance Ijara. | G43: Yes
D44: 10.4.1.3 Commodity Murabaha
D45: Create and Disburse Commodity Murabaha Finance (Manual) (IF) | E45: The process describes activities involved in maintaining manual disbursement in commodity Murabaha Finance. | G45: Yes
D46: Create and Disburse Commodity Murabaha Finance (Scheduled) (IF) | E46: The process describes activities involved in maintaining scheduled disbursement in commodity Murabaha Finance. | G46: Yes
D47: Create Commodity Murabaha Contract (IF) | E47: Commodity Murabaha is a Murabaha based short term placement operation that involves the purchase and sale of commodities in the international exchange. The process begins with the receipt of completed finance application from the Customer. Bank will approve the purchase of commodity from Buy Broker after capturing the Collateral and setting up limit. | G47: Yes
D48: Initiate Commodity Murabaha Sale (IF) | E48: The process describes the process flow for initiating Commodity Murabaha sale. | G48: Yes
D49: Perform Commodity Murabaha Contract Status Change (IF) | E49: This process describes the activities involved in purchase of approved commodity from Buy Broker. Post purchase, if possession of the commodity is taken by the Customer, the commodity cannot be returned/sold and Commodity Murabaha arrangement gets created. Based on the customer request, the contract gets updated and accounting entries generated | G49: Yes
D50: Receive Commodity Murabaha Finance Application (IF) | E50: The process deals with various activities associated with receipt of new financing request from a Customer and the processing of the application under Commodity Murabaha. | G50: Yes
C51: 10.4.2 Profit Accrual Sale | G51: =COUNTIF(G52:G93,"Yes") -> 36
D52: 10.4.2.1 Diminishing Musharaka
D53: Create and Disburse Diminishing Musharaka Finance (Manual) (IF) | E53: The process describes activities involved in maintaining manual disbursement in Musharaka Finance. | G53: Yes
D54: Create and Disburse Diminishing Musharaka Finance (Scheduled) (IF) | E54: The process describes activities involved in maintaining scheduled disbursement in Diminishing Musharaka Finance. | G54: Yes
D55: Create Diminishing Musharaka Contract (IF) | E55: The Islamic bank enters with a client into a partnership in which they both invest in the equity capital required to finance a project. This process begins with the receipt of completed finance application from the Customer. It is acknowledged at the front office and forwarded to the credit department for capturing collateral details and setting up limit. Asset details are captured and approved for purchase of Asset/ Commodity. | G55: Yes
D56: Initiate Diminishing Musharaka Sale (IF) | E56: The process describes the process flow for initiating Musharaka sale. | G56: Yes
D57: Perform Diminishing Musharaka Contract Status Change (IF) | E57: This process is used to purchase the approved asset from the Vendor. The contract workflow status is modified from "Approval " to "Purchase". | G57: Yes
D58: Receive Diminishing Musharaka Finance Application (IF) | E58: The process deals with various activities associated with receipt of new financing request from a Customer and the processing of the application under Musharaka. | G58: Yes
D59: 10.4.2.2 Mudaraba Finance
D60: Amend Mudaraba Facility (IF) | E60: This process describes the activities involved in amending an existing Mudaraba facility arrangement account by a bank or as requested by a customer. The following amendments are allowed in a facility arrangement. - Inclusion/ removal of allowed products (drawing) - Renegotiate Arrangement - Update Account Details and Posting Restrictions - Adjust Balances and Bills - Change Customer - Change Charges - Change Profit - Update Limit Link. | G60: Yes
D61: Close Mudaraba Facility (IF) | E61: This process describes the activities involved in the closure of a Mudaraba facility arrangement. A facility can be closed only if all underlying finances are closed. A payment order is initiated for repayment of the facility outstanding amounts. Post settlement the underlying finance arrangements and facility are auto closed. | G61: Yes
D62: Create and Disburse Mudaraba Finance (Manual) (IF) | E62: The process describes activities involved in maintaining manual disbursement in Mudaraba Finance. | G62: Yes
D63: Create and Disburse Mudaraba Finance (Scheduled) (IF) | E63: The process describes activities involved in maintaining Scheduled disbursement in Mudaraba Finance. | G63: Yes
D64: Create Mudaraba Facility (IF) | E64: This process describes the activities involved in creating a standalone Mudaraba facility arrangement for a customer. Facility arrangement details, variable or fixed limit, commitment amortisation schedule and payment method are captured based on customer request. During the facility's tenure, the customer can utilise the agreed amount by performing a drawdown on the facility and creating finance arrangements. | G64: Yes
D65: Perform Disbursement of Mudaraba Drawings Under Facility Arrangement (IF) | E65: This process describes the activities involved in the disbursement of funds from a drawing arrangement. The Payout Beneficiary for the arrangement is checked and funds are disbursed as per schedule. If Payout Beneficiary is unavailable the funds are disbursed manually. | G65: Yes
D66: Perform Mudaraba Drawings Under Facility Arrangement (IF) | E66: This process describes the activities involved in performing the Mudaraba drawdown by creating arrangements under the facility based on the allowed products set. A drawdown cannot be performed for a blocked facility or in case of insufficient commitment balance. Arrangement details along with Repayment Method, Repayment Schedule and Settlement Instructions are captured. | G66: Yes
D67: Perform Declaration of Profit (IF) | E67: The process describes workflow for declaration of profit for Mudaraba finance. | G67: Yes
D68: Receive Mudaraba Finance Application (IF) | E68: The process deals with various activities associated with receipt of new financing request from a Customer and the processing of the application under Mudaraba. | G68: Yes
D69: Perform Impairment (Write-Off) (IF) | E69: This process depicts the flow of writing-off Mudaraba Finance Overdue balance. | G69: Yes
D70: 10.4.2.3 Forward Ijara
D71: Create and Disburse Forward Ijara Finance (Manual) (IF) | E71: The process describes activities involved in maintaining manual disbursement in Forward Ijara Finance. | G71: Yes
D72: Create and Disburse Forward Ijara Finance (Scheduled) (IF) | E72: The process describes activities involved in maintaining scheduled disbursement in Forward Ijara Finance. | G72: Yes
D73: Create Forward Ijara Contract (IF) | E73: The process describes the initiation into Forward Ijara Contract process work flow. | G73: Yes
D74: Forward Ijara down payment settlement (IF) | E74: This process describes settlement of Ijara finance contract with the down payment amount collected from the customer. | G74: Yes
D75: Initiate Forward Ijara Sale (IF) | E75: The process describes the process flow for initiating Forward Ijara sale. | G75: Yes
D76: Receive Forward Ijara Finance Application (IF) | E76: The process deals with various activities associated with receipt of new financing request from a Customer and the processing of the application under Forward Ijara. | G76: Yes
D77: 10.4.2.4 Construction Finance
